{
"meta":{"test_sets":[],"test_metrics":[],"learn_metrics":[{"best_value":"Min","name":"RMSE"}],"launch_mode":"Train","parameters":"","iteration_count":1000,"learn_sets":["learn"],"name":"experiment"},
"iterations":[
{"learn":[14.61840273],"iteration":0,"passed_time":0.004097193946,"remaining_time":4.093096752},
{"learn":[14.24923312],"iteration":1,"passed_time":0.004481613173,"remaining_time":2.236324973},
{"learn":[13.90182089],"iteration":2,"passed_time":0.004735614864,"remaining_time":1.573802673},
{"learn":[13.56965751],"iteration":3,"passed_time":0.005004741656,"remaining_time":1.246180672},
{"learn":[13.21813324],"iteration":4,"passed_time":0.005348493944,"remaining_time":1.064350295},
{"learn":[12.87766915],"iteration":5,"passed_time":0.00567278777,"remaining_time":0.9397918406},
{"learn":[12.60094572],"iteration":6,"passed_time":0.006008040002,"remaining_time":0.8522833889},
{"learn":[12.30990148],"iteration":7,"passed_time":0.006348292268,"remaining_time":0.7871882412},
{"learn":[12.02255494],"iteration":8,"passed_time":0.006605335646,"remaining_time":0.7273208472},
{"learn":[11.74885767],"iteration":9,"passed_time":0.00681471204,"remaining_time":0.674656492},
{"learn":[11.50452691],"iteration":10,"passed_time":0.007026671785,"remaining_time":0.6317616723},
{"learn":[11.28041387],"iteration":11,"passed_time":0.007296965251,"remaining_time":0.6007834723},
{"learn":[11.03293286],"iteration":12,"passed_time":0.007637550852,"remaining_time":0.5798663608},
{"learn":[10.79848245],"iteration":13,"passed_time":0.007854468963,"remaining_time":0.5531790284},
{"learn":[10.56070532],"iteration":14,"passed_time":0.00807130374,"remaining_time":0.5300156123},
{"learn":[10.32201325],"iteration":15,"passed_time":0.008281263471,"remaining_time":0.5092977035},
{"learn":[10.12946456],"iteration":16,"passed_time":0.008473306416,"remaining_time":0.4899564828},
{"learn":[9.91846997],"iteration":17,"passed_time":0.008691641204,"remaining_time":0.4741773145},
{"learn":[9.71526746],"iteration":18,"passed_time":0.008929601121,"remaining_time":0.4610494053},
{"learn":[9.519952706],"iteration":19,"passed_time":0.00921022799,"remaining_time":0.4513011715},
{"learn":[9.339609628],"iteration":20,"passed_time":0.009477813105,"remaining_time":0.4418466204},
{"learn":[9.16395548],"iteration":21,"passed_time":0.009746148225,"remaining_time":0.4332605893},
{"learn":[9.013956979],"iteration":22,"passed_time":0.01015969264,"remaining_time":0.4315660745},
{"learn":[8.847284645],"iteration":23,"passed_time":0.01041269433,"remaining_time":0.4234495694},
{"learn":[8.713947105],"iteration":24,"passed_time":0.01070686295,"remaining_time":0.4175676552},
{"learn":[8.569304051],"iteration":25,"passed_time":0.01092657275,"remaining_time":0.4093262254},
{"learn":[8.437364042],"iteration":26,"passed_time":0.01116757436,"remaining_time":0.4024462907},
{"learn":[8.316802857],"iteration":27,"passed_time":0.01163891083,"remaining_time":0.4040364758},
{"learn":[8.179195178],"iteration":28,"passed_time":0.01187620407,"remaining_time":0.3976480743},
{"learn":[8.057538492],"iteration":29,"passed_time":0.01210283058,"remaining_time":0.3913248555},
{"learn":[7.955798557],"iteration":30,"passed_time":0.01246199964,"remaining_time":0.3895379888},
{"learn":[7.841586126],"iteration":31,"passed_time":0.01276900168,"remaining_time":0.386262301},
{"learn":[7.726888871],"iteration":32,"passed_time":0.01299912822,"remaining_time":0.380913848},
{"learn":[7.618089792],"iteration":33,"passed_time":0.01326417165,"remaining_time":0.3768585239},
{"learn":[7.528943287],"iteration":34,"passed_time":0.01347154803,"remaining_time":0.3714298242},
{"learn":[7.430217175],"iteration":35,"passed_time":0.01366788267,"remaining_time":0.3659955248},
{"learn":[7.338074232],"iteration":36,"passed_time":0.0138778424,"remaining_time":0.3611989792},
{"learn":[7.248620995],"iteration":37,"passed_time":0.01408984381,"remaining_time":0.3566955197},
{"learn":[7.158820217],"iteration":38,"passed_time":0.01430222023,"remaining_time":0.3524213753},
{"learn":[7.081860503],"iteration":39,"passed_time":0.01446747133,"remaining_time":0.3472193118},
{"learn":[6.999718555],"iteration":40,"passed_time":0.01467922274,"remaining_time":0.3433506001},
{"learn":[6.939337185],"iteration":41,"passed_time":0.01492605771,"remaining_time":0.3404562688},
{"learn":[6.866739025],"iteration":42,"passed_time":0.0151896428,"remaining_time":0.3380578642},
{"learn":[6.800026187],"iteration":43,"passed_time":0.01541689431,"remaining_time":0.3349670674},
{"learn":[6.734830608],"iteration":44,"passed_time":0.01569227115,"remaining_time":0.3330248655},
{"learn":[6.667172925],"iteration":45,"passed_time":0.0160008982,"remaining_time":0.3318447149},
{"learn":[6.613030709],"iteration":46,"passed_time":0.01625319155,"remaining_time":0.3295593946},
{"learn":[6.561261141],"iteration":47,"passed_time":0.01653365175,"remaining_time":0.3279174264},
{"learn":[6.503244446],"iteration":48,"passed_time":0.01682019532,"remaining_time":0.326449097},
{"learn":[6.447969931],"iteration":49,"passed_time":0.01722944805,"remaining_time":0.3273595129},
{"learn":[6.397727361],"iteration":50,"passed_time":0.01747124133,"remaining_time":0.325102118},
{"learn":[6.356139726],"iteration":51,"passed_time":0.01790178586,"remaining_time":0.3263633268},
{"learn":[6.308643885],"iteration":52,"passed_time":0.01820945457,"remaining_time":0.32536516},
{"learn":[6.263511989],"iteration":53,"passed_time":0.01845199786,"remaining_time":0.3232516661},
{"learn":[6.225281986],"iteration":54,"passed_time":0.01866674929,"remaining_time":0.3207286923},
{"learn":[6.185498113],"iteration":55,"passed_time":0.01887475067,"remaining_time":0.3181743685},
{"learn":[6.151652526],"iteration":56,"passed_time":0.01907058531,"remaining_time":0.3155010868},
{"learn":[6.111485651],"iteration":57,"passed_time":0.01929321179,"remaining_time":0.3133483708},
{"learn":[6.077020887],"iteration":58,"passed_time":0.01949337979,"remaining_time":0.3109028878},
{"learn":[6.038716705],"iteration":59,"passed_time":0.01968108937,"remaining_time":0.3083370668},
{"learn":[6.009225669],"iteration":60,"passed_time":0.01983309038,"remaining_time":0.3052995389},
{"learn":[5.976288245],"iteration":61,"passed_time":0.02006088357,"remaining_time":0.3035017546},
{"learn":[5.943755976],"iteration":62,"passed_time":0.02025888489,"remaining_time":0.3013107165},
{"learn":[5.912313158],"iteration":63,"passed_time":0.02048859475,"remaining_time":0.2996456982},
{"learn":[5.880093508],"iteration":64,"passed_time":0.02075763821,"remaining_time":0.2985906419},
{"learn":[5.853093316],"iteration":65,"passed_time":0.02096005622,"remaining_time":0.2966165532},
{"learn":[5.825774591],"iteration":66,"passed_time":0.02119784947,"remaining_time":0.2951879635},
{"learn":[5.799601392],"iteration":67,"passed_time":0.02146960128,"remaining_time":0.2942598293},
{"learn":[5.778726266],"iteration":68,"passed_time":0.021727478,"remaining_time":0.2931635075},
{"learn":[5.756221875],"iteration":69,"passed_time":0.02202006328,"remaining_time":0.2925522693},
{"learn":[5.734428546],"iteration":70,"passed_time":0.02237031561,"remaining_time":0.2927045522},
{"learn":[5.714565431],"iteration":71,"passed_time":0.02267215095,"remaining_time":0.2922188345},
{"learn":[5.68978697],"iteration":72,"passed_time":0.02289502744,"remaining_time":0.2907354854},
{"learn":[5.665438055],"iteration":73,"passed_time":0.02321469623,"remaining_time":0.290497415},
{"learn":[5.644061884],"iteration":74,"passed_time":0.02341086421,"remaining_time":0.2887339919},
{"learn":[5.627823576],"iteration":75,"passed_time":0.0237498248,"remaining_time":0.2887478699},
{"learn":[5.609552479],"iteration":76,"passed_time":0.02403549337,"remaining_time":0.2881137711},
{"learn":[5.597629723],"iteration":77,"passed_time":0.0241264523,"remaining_time":0.2851870388},
{"learn":[5.57836272],"iteration":78,"passed_time":0.02433274534,"remaining_time":0.2836766894},
{"learn":[5.562997508],"iteration":79,"passed_time":0.02452424662,"remaining_time":0.2820288361},
{"learn":[5.54507544],"iteration":80,"passed_time":0.02475591483,"remaining_time":0.2808726633},
{"learn":[5.528654451],"iteration":81,"passed_time":0.02512033392,"remaining_time":0.2812252017},
{"learn":[5.513890866],"iteration":82,"passed_time":0.02545379448,"remaining_time":0.2812184281},
{"learn":[5.493664034],"iteration":83,"passed_time":0.02587379727,"remaining_time":0.2821475988},
{"learn":[5.47639589],"iteration":84,"passed_time":0.02615250746,"remaining_time":0.2815240509},
{"learn":[5.463878397],"iteration":85,"passed_time":0.02636225886,"remaining_time":0.2801756348},
{"learn":[5.45112915],"iteration":86,"passed_time":0.02660117711,"remaining_time":0.2791594794},
{"learn":[5.441275129],"iteration":87,"passed_time":0.02676676155,"remaining_time":0.2774009833},
{"learn":[5.43116516],"iteration":88,"passed_time":0.02702647161,"remaining_time":0.2766417488},
{"learn":[5.417487827],"iteration":89,"passed_time":0.02726068151,"remaining_time":0.2756357797},
{"learn":[5.403940845],"iteration":90,"passed_time":0.02745743282,"remaining_time":0.2742725981},
{"learn":[5.394651676],"iteration":91,"passed_time":0.02769718441,"remaining_time":0.2733591679},
{"learn":[5.3831013],"iteration":92,"passed_time":0.02791414419,"remaining_time":0.2722379439},
{"learn":[5.372934159],"iteration":93,"passed_time":0.02810693714,"remaining_time":0.2709030324},
{"learn":[5.358796437],"iteration":94,"passed_time":0.02838943902,"remaining_time":0.2704467612},
{"learn":[5.346521859],"iteration":95,"passed_time":0.02873027462,"remaining_time":0.2705434194},
{"learn":[5.334090056],"iteration":96,"passed_time":0.02899402638,"remaining_time":0.2699134621},
{"learn":[5.325183269],"iteration":97,"passed_time":0.02949319637,"remaining_time":0.271457787},
{"learn":[5.313791394],"iteration":98,"passed_time":0.0297528231,"remaining_time":0.2707807436},
{"learn":[5.303985929],"iteration":99,"passed_time":0.02997228289,"remaining_time":0.269750546},
{"learn":[5.297836894],"iteration":100,"passed_time":0.03017832593,"remaining_time":0.2686169803},
{"learn":[5.290050005],"iteration":101,"passed_time":0.03039116068,"remaining_time":0.267561395},
{"learn":[5.282340666],"iteration":102,"passed_time":0.03066824586,"remaining_time":0.2670817139},
{"learn":[5.27034746],"iteration":103,"passed_time":0.03093133095,"remaining_time":0.2664853128},
{"learn":[5.263372567],"iteration":104,"passed_time":0.03117124921,"remaining_time":0.2656977909},
{"learn":[5.253023987],"iteration":105,"passed_time":0.03146416783,"remaining_time":0.2653676041},
{"learn":[5.244185028],"iteration":106,"passed_time":0.03174525303,"remaining_time":0.2649393547},
{"learn":[5.237331643],"iteration":107,"passed_time":0.0321616308,"remaining_time":0.265631247},
{"learn":[5.23014088],"iteration":108,"passed_time":0.03236279881,"remaining_time":0.2645436123},
{"learn":[5.225617974],"iteration":109,"passed_time":0.0325217582,"remaining_time":0.2631305891},
{"learn":[5.214631422],"iteration":110,"passed_time":0.03273071793,"remaining_time":0.2621406147},
{"learn":[5.208356201],"iteration":111,"passed_time":0.03301896985,"remaining_time":0.2617932609},
{"learn":[5.201888834],"iteration":112,"passed_time":0.03320805444,"remaining_time":0.2606685335},
{"learn":[5.197321578],"iteration":113,"passed_time":0.03341838917,"remaining_time":0.2597253755},
{"learn":[5.191822148],"iteration":114,"passed_time":0.03361768216,"remaining_time":0.2587099888},
{"learn":[5.187785268],"iteration":115,"passed_time":0.03380230839,"remaining_time":0.2575969019},
{"learn":[5.180281863],"iteration":116,"passed_time":0.03401043478,"remaining_time":0.256677042},
{"learn":[5.173263116],"iteration":117,"passed_time":0.03437552054,"remaining_time":0.2569424502},
{"learn":[5.166916171],"iteration":118,"passed_time":0.03458118858,"remaining_time":0.2560170348},
{"learn":[5.156800075],"iteration":119,"passed_time":0.03486577381,"remaining_time":0.2556823413},
{"learn":[5.15223655],"iteration":120,"passed_time":0.0350601501,"remaining_time":0.2546931565},
{"learn":[5.144342438],"iteration":121,"passed_time":0.03525315139,"remaining_time":0.2537071059},
{"learn":[5.135048255],"iteration":122,"passed_time":0.03542861089,"remaining_time":0.252608876},
{"learn":[5.129560122],"iteration":123,"passed_time":0.03578423826,"remaining_time":0.2527983283},
{"learn":[5.124416079],"iteration":124,"passed_time":0.0361165738,"remaining_time":0.2528160166},
{"learn":[5.119075784],"iteration":125,"passed_time":0.03638661727,"remaining_time":0.2523960595},
{"learn":[5.113397932],"iteration":126,"passed_time":0.03672549452,"remaining_time":0.2524516277},
{"learn":[5.109988107],"iteration":127,"passed_time":0.03703328824,"remaining_time":0.2522892761},
{"learn":[5.102546616],"iteration":128,"passed_time":0.03728308157,"remaining_time":0.2517330546},
{"learn":[5.092528818],"iteration":129,"passed_time":0.03760229203,"remaining_time":0.2516461082},
{"learn":[5.08659301],"iteration":130,"passed_time":0.03779887667,"remaining_time":0.2507421666},
{"learn":[5.07858737],"iteration":131,"passed_time":0.03799529464,"remaining_time":0.2498478466},
{"learn":[5.069941527],"iteration":132,"passed_time":0.03819733766,"remaining_time":0.2490006898},
{"learn":[5.062790926],"iteration":133,"passed_time":0.03840533904,"remaining_time":0.2482016687},
{"learn":[5.057800561],"iteration":134,"passed_time":0.03860559037,"remaining_time":0.2473617457},
{"learn":[5.050647005],"iteration":135,"passed_time":0.03882321682,"remaining_time":0.2466416128},
{"learn":[5.044560184],"iteration":136,"passed_time":0.03910901039,"remaining_time":0.2463582188},
{"learn":[5.038708529],"iteration":137,"passed_time":0.03939792898,"remaining_time":0.24609431},
{"learn":[5.033743628],"iteration":138,"passed_time":0.03963901392,"remaining_time":0.2455337481},
{"learn":[5.029532025],"iteration":139,"passed_time":0.04004380828,"remaining_time":0.2459833937},
{"learn":[5.027960582],"iteration":140,"passed_time":0.04017093413,"remaining_time":0.2447293079},
{"learn":[5.019064862],"iteration":141,"passed_time":0.04040301901,"remaining_time":0.2441252839},
{"learn":[5.01052462],"iteration":142,"passed_time":0.04062006212,"remaining_time":0.2434363163},
{"learn":[5.006764548],"iteration":143,"passed_time":0.04083031352,"remaining_time":0.2427135304},
{"learn":[5.002821354],"iteration":144,"passed_time":0.04106477342,"remaining_time":0.2421405605},
{"learn":[4.998631929],"iteration":145,"passed_time":0.04128019152,"remaining_time":0.2414608463},
{"learn":[4.995072644],"iteration":146,"passed_time":0.04151935978,"remaining_time":0.2409252645},
{"learn":[4.992578306],"iteration":147,"passed_time":0.04176636142,"remaining_time":0.2404387833},
{"learn":[4.988077683],"iteration":148,"passed_time":0.04206190505,"remaining_time":0.2402327597},
{"learn":[4.983016414],"iteration":149,"passed_time":0.0422690731,"remaining_time":0.2395247476},
{"learn":[4.979638308],"iteration":150,"passed_time":0.04245699102,"remaining_time":0.2387151349},
{"learn":[4.97464965],"iteration":151,"passed_time":0.04267115911,"remaining_time":0.2380601508},
{"learn":[4.97069099],"iteration":152,"passed_time":0.04289495227,"remaining_time":0.2374642129},
{"learn":[4.967105811],"iteration":153,"passed_time":0.04308428686,"remaining_time":0.2366838096},
{"learn":[4.958361862],"iteration":154,"passed_time":0.04329724661,"remaining_time":0.2360398283},
{"learn":[4.955646214],"iteration":155,"passed_time":0.04345683101,"remaining_time":0.2351125985},
{"learn":[4.951042725],"iteration":156,"passed_time":0.04366337405,"remaining_time":0.2344472887},
{"learn":[4.947081295],"iteration":157,"passed_time":0.04416825241,"remaining_time":0.2353776489},
{"learn":[4.943680648],"iteration":158,"passed_time":0.04458450518,"remaining_time":0.2358211878},
{"learn":[4.94198868],"iteration":159,"passed_time":0.04489209056,"remaining_time":0.2356834755},
{"learn":[4.939540796],"iteration":160,"passed_time":0.0450971336,"remaining_time":0.2350092863},
{"learn":[4.936646974],"iteration":161,"passed_time":0.04532321844,"remaining_time":0.2344497349},
{"learn":[4.928332184],"iteration":162,"passed_time":0.04557105342,"remaining_time":0.2340059614},
{"learn":[4.923158129],"iteration":163,"passed_time":0.04580968001,"remaining_time":0.2335176371},
{"learn":[4.919365146],"iteration":164,"passed_time":0.04603005647,"remaining_time":0.2329399828},
{"learn":[4.917011537],"iteration":165,"passed_time":0.04623184948,"remaining_time":0.2322732679},
{"learn":[4.913614316],"iteration":166,"passed_time":0.04645214262,"remaining_time":0.2317044},
{"learn":[4.910191525],"iteration":167,"passed_time":0.04664118554,"remaining_time":0.2309849189},
{"learn":[4.906078661],"iteration":168,"passed_time":0.04690735398,"remaining_time":0.2306509536},
{"learn":[4.898256226],"iteration":169,"passed_time":0.04717910579,"remaining_time":0.2303450459},
{"learn":[4.894356912],"iteration":170,"passed_time":0.04742452409,"remaining_time":0.2299118741},
{"learn":[4.889421364],"iteration":171,"passed_time":0.04766190067,"remaining_time":0.229442173},
{"learn":[4.887478324],"iteration":172,"passed_time":0.04788990219,"remaining_time":0.2289303417},
{"learn":[4.883598745],"iteration":173,"passed_time":0.04809832025,"remaining_time":0.2283288076},
{"learn":[4.877834949],"iteration":174,"passed_time":0.04831273834,"remaining_time":0.2277600522},
{"learn":[4.874227373],"iteration":175,"passed_time":0.04859394855,"remaining_time":0.2275080318},
{"learn":[4.871875237],"iteration":176,"passed_time":0.04888649216,"remaining_time":0.2273083788},
{"learn":[4.868382273],"iteration":177,"passed_time":0.04909620189,"remaining_time":0.226725157},
{"learn":[4.866238709],"iteration":178,"passed_time":0.04930361994,"remaining_time":0.2261355976},
{"learn":[4.860394991],"iteration":179,"passed_time":0.04951999638,"remaining_time":0.2255910946},
{"learn":[4.857550158],"iteration":180,"passed_time":0.04971262266,"remaining_time":0.2249427512},
{"learn":[4.851994933],"iteration":181,"passed_time":0.04991616568,"remaining_time":0.2243484809},
{"learn":[4.847542445],"iteration":182,"passed_time":0.05018712582,"remaining_time":0.2240594634},
{"learn":[4.843177146],"iteration":183,"passed_time":0.05036783536,"remaining_time":0.2233704003},
{"learn":[4.838295687],"iteration":184,"passed_time":0.05059383686,"remaining_time":0.2228863624},
{"learn":[4.834176776],"iteration":185,"passed_time":0.05078558814,"remaining_time":0.2222552083},
{"learn":[4.829505215],"iteration":186,"passed_time":0.05103113144,"remaining_time":0.2218626196},
{"learn":[4.826555906],"iteration":187,"passed_time":0.0512549246,"remaining_time":0.221377653},
{"learn":[4.824230067],"iteration":188,"passed_time":0.05143292578,"remaining_time":0.2206989567},
{"learn":[4.81956046],"iteration":189,"passed_time":0.05165317725,"remaining_time":0.2202056504},
{"learn":[4.81598863],"iteration":190,"passed_time":0.05186013696,"remaining_time":0.2196589047},
{"learn":[4.812171749],"iteration":191,"passed_time":0.05205467992,"remaining_time":0.2190634447},
{"learn":[4.809262098],"iteration":192,"passed_time":0.05225880628,"remaining_time":0.2185122107},
{"learn":[4.806521347],"iteration":193,"passed_time":0.05251064129,"remaining_time":0.2181627674},
{"learn":[4.803859652],"iteration":194,"passed_time":0.05279847654,"remaining_time":0.2179629416},
{"learn":[4.800811465],"iteration":195,"passed_time":0.05307156169,"remaining_time":0.2177017122},
{"learn":[4.797696136],"iteration":196,"passed_time":0.05337218869,"remaining_time":0.217552627},
{"learn":[4.794073092],"iteration":197,"passed_time":0.05361602365,"remaining_time":0.2171719746},
{"learn":[4.792159559],"iteration":198,"passed_time":0.05383740012,"remaining_time":0.216702299},
{"learn":[4.787318874],"iteration":199,"passed_time":0.05403969314,"remaining_time":0.2161587725},
{"learn":[4.783239093],"iteration":200,"passed_time":0.05423261109,"remaining_time":0.2155813744},
{"learn":[4.77813436],"iteration":201,"passed_time":0.05443848746,"remaining_time":0.2150589752},
{"learn":[4.772528873],"iteration":202,"passed_time":0.05465119721,"remaining_time":0.214566523},
{"learn":[4.767576809],"iteration":203,"passed_time":0.05485340689,"remaining_time":0.2140358426},
{"learn":[4.764940622],"iteration":204,"passed_time":0.05505915826,"remaining_time":0.2135221015},
{"learn":[4.763248503],"iteration":205,"passed_time":0.05527090967,"remaining_time":0.2130344771},
{"learn":[4.759428819],"iteration":206,"passed_time":0.05554749484,"remaining_time":0.2127978909},
{"learn":[4.758457514],"iteration":207,"passed_time":0.05595408088,"remaining_time":0.2130559234},
{"learn":[4.755866721],"iteration":208,"passed_time":0.05621095759,"remaining_time":0.2127409926},
{"learn":[4.749796347],"iteration":209,"passed_time":0.05643608409,"remaining_time":0.2123071735},
{"learn":[4.746103273],"iteration":210,"passed_time":0.05674037779,"remaining_time":0.2121713653},
{"learn":[4.744612208],"iteration":211,"passed_time":0.05702562968,"remaining_time":0.2119631896},
{"learn":[4.740298891],"iteration":212,"passed_time":0.05740921557,"remaining_time":0.2121176181},
{"learn":[4.738108482],"iteration":213,"passed_time":0.05759480014,"remaining_time":0.21153978},
{"learn":[4.734143318],"iteration":214,"passed_time":0.05785976024,"remaining_time":0.2112554037},
{"learn":[4.728948747],"iteration":215,"passed_time":0.0580790117,"remaining_time":0.2108053017},
{"learn":[4.724989411],"iteration":216,"passed_time":0.05826288792,"remaining_time":0.2102296831},
{"learn":[4.721281071],"iteration":217,"passed_time":0.05865576554,"remaining_time":0.2104073791},
{"learn":[4.718391],"iteration":218,"passed_time":0.05890510053,"remaining_time":0.2100679613},
{"learn":[4.714249126],"iteration":219,"passed_time":0.0591150186,"remaining_time":0.2095896114},
{"learn":[4.713344641],"iteration":220,"passed_time":0.0593560202,"remaining_time":0.2092232567},
{"learn":[4.709936204],"iteration":221,"passed_time":0.0595568132,"remaining_time":0.2087171201},
{"learn":[4.706919585],"iteration":222,"passed_time":0.05999164943,"remaining_time":0.2090292},
{"learn":[4.705585106],"iteration":223,"passed_time":0.06023073436,"remaining_time":0.2086564726},
{"learn":[4.700742471],"iteration":224,"passed_time":0.06043569406,"remaining_time":0.2081673906},
{"learn":[4.696484996],"iteration":225,"passed_time":0.06068844574,"remaining_time":0.2078445},
{"learn":[4.691729807],"iteration":226,"passed_time":0.06094082242,"remaining_time":0.2075209504},
{"learn":[4.687217003],"iteration":227,"passed_time":0.06111386524,"remaining_time":0.2069294034},
{"learn":[4.683852236],"iteration":228,"passed_time":0.0613237833,"remaining_time":0.2064656634},
{"learn":[4.680091882],"iteration":229,"passed_time":0.0615184096,"remaining_time":0.2059529365},
{"learn":[4.677942739],"iteration":230,"passed_time":0.06174478611,"remaining_time":0.2055486602},
{"learn":[4.677226874],"iteration":231,"passed_time":0.06202599631,"remaining_time":0.2053274361},
{"learn":[4.673894112],"iteration":232,"passed_time":0.06234712345,"remaining_time":0.2052370974},
{"learn":[4.668580623],"iteration":233,"passed_time":0.06257704165,"remaining_time":0.2048462133},
{"learn":[4.666637775],"iteration":234,"passed_time":0.0627849597,"remaining_time":0.2043850816},
{"learn":[4.663735458],"iteration":235,"passed_time":0.06304246141,"remaining_time":0.2040866124},
{"learn":[4.659397098],"iteration":236,"passed_time":0.06332008826,"remaining_time":0.2038532799},
{"learn":[4.657647969],"iteration":237,"passed_time":0.06350825618,"remaining_time":0.2033331563},
{"learn":[4.648788985],"iteration":238,"passed_time":0.06376959125,"remaining_time":0.2030487822},
{"learn":[4.646917772],"iteration":239,"passed_time":0.06398096766,"remaining_time":0.2026063976},
{"learn":[4.644027552],"iteration":240,"passed_time":0.06419226073,"remaining_time":0.2021656676},
{"learn":[4.639469654],"iteration":241,"passed_time":0.06440951218,"remaining_time":0.2017454968},
{"learn":[4.637579223],"iteration":242,"passed_time":0.06463343034,"remaining_time":0.2013477645},
{"learn":[4.633950288],"iteration":243,"passed_time":0.06501209953,"remaining_time":0.2014309313},
{"learn":[4.631093095],"iteration":244,"passed_time":0.06523293433,"remaining_time":0.2010239405},
{"learn":[4.628248883],"iteration":245,"passed_time":0.0654433524,"remaining_time":0.2005865354},
{"learn":[4.626584984],"iteration":246,"passed_time":0.06565943717,"remaining_time":0.2001682437},
{"learn":[4.626177967],"iteration":247,"passed_time":0.06586068851,"remaining_time":0.1997066039},
{"learn":[4.624514108],"iteration":248,"passed_time":0.06608148165,"remaining_time":0.1993059948},
{"learn":[4.621888615],"iteration":249,"passed_time":0.06626648288,"remaining_time":0.1987994486},
{"learn":[4.621499528],"iteration":250,"passed_time":0.06649365106,"remaining_time":0.1984212934},
{"learn":[4.616228379],"iteration":251,"passed_time":0.0667107775,"remaining_time":0.19801453},
{"learn":[4.61116647],"iteration":252,"passed_time":0.06700615447,"remaining_time":0.1978403059},
{"learn":[4.607850846],"iteration":253,"passed_time":0.06723569766,"remaining_time":0.1974717735},
{"learn":[4.601085249],"iteration":254,"passed_time":0.06743624067,"remaining_time":0.1970196051},
{"learn":[4.596473024],"iteration":255,"passed_time":0.06763590866,"remaining_time":0.1965668596},
{"learn":[4.59358806],"iteration":256,"passed_time":0.06787691027,"remaining_time":0.196235581},
{"learn":[4.590151083],"iteration":257,"passed_time":0.06810366178,"remaining_time":0.1958640195},
{"learn":[4.588454423],"iteration":258,"passed_time":0.06840824714,"remaining_time":0.1957162592},
{"learn":[4.585639555],"iteration":259,"passed_time":0.06871866587,"remaining_time":0.1955838952},
{"learn":[4.582239473],"iteration":260,"passed_time":0.0690429597,"remaining_time":0.1954894529},
{"learn":[4.579625359],"iteration":261,"passed_time":0.06934687839,"remaining_time":0.1953358636},
{"learn":[4.578006855],"iteration":262,"passed_time":0.06967538058,"remaining_time":0.1952500209},
{"learn":[4.576553828],"iteration":263,"passed_time":0.07004625804,"remaining_time":0.195280477},
{"learn":[4.573254252],"iteration":264,"passed_time":0.07026705118,"remaining_time":0.1948916325},
{"learn":[4.570974029],"iteration":265,"passed_time":0.07053613631,"remaining_time":0.1946373085},
{"learn":[4.567458686],"iteration":266,"passed_time":0.07077159621,"remaining_time":0.1942905619},
{"learn":[4.561649621],"iteration":267,"passed_time":0.07106280648,"remaining_time":0.1940969192},
{"learn":[4.556178356],"iteration":268,"passed_time":0.07133897499,"remaining_time":0.1938616755},
{"learn":[4.553073529],"iteration":269,"passed_time":0.07152622623,"remaining_time":0.1933857228},
{"learn":[4.547634042],"iteration":270,"passed_time":0.07179806138,"remaining_time":0.1931394345},
{"learn":[4.540018486],"iteration":271,"passed_time":0.07199735437,"remaining_time":0.1926988014},
{"learn":[4.539162983],"iteration":272,"passed_time":0.07243610729,"remaining_time":0.192897619},
{"learn":[4.538861759],"iteration":273,"passed_time":0.07261365014,"remaining_time":0.1923996715},
{"learn":[4.535641698],"iteration":274,"passed_time":0.07282219319,"remaining_time":0.1919857821},
{"learn":[4.532118148],"iteration":275,"passed_time":0.073043028,"remaining_time":0.1916056242},
{"learn":[4.531222455],"iteration":276,"passed_time":0.07322790423,"remaining_time":0.1911327609},
{"learn":[4.526167926],"iteration":277,"passed_time":0.0734544474,"remaining_time":0.1907701835},
{"learn":[4.523032382],"iteration":278,"passed_time":0.07368619895,"remaining_time":0.190422041},
{"learn":[4.516682874],"iteration":279,"passed_time":0.07389253365,"remaining_time":0.1900093723},
{"learn":[4.514627004],"iteration":280,"passed_time":0.07416099377,"remaining_time":0.1897571335},
{"learn":[4.514324578],"iteration":281,"passed_time":0.07438720361,"remaining_time":0.1893972064},
{"learn":[4.511928715],"iteration":282,"passed_time":0.0746811639,"remaining_time":0.1892098746},
{"learn":[4.509359789],"iteration":283,"passed_time":0.07497112417,"remaining_time":0.1890117074},
{"learn":[4.509068593],"iteration":284,"passed_time":0.07521304245,"remaining_time":0.1886923696},
{"learn":[4.508384613],"iteration":285,"passed_time":0.07542908555,"remaining_time":0.1883089758},
{"learn":[4.503696461],"iteration":286,"passed_time":0.07563275357,"remaining_time":0.1878960045},
{"learn":[4.501801159],"iteration":287,"passed_time":0.07584746334,"remaining_time":0.1875117844},
{"learn":[4.49819942],"iteration":288,"passed_time":0.07604629799,"remaining_time":0.1870896812},
{"learn":[4.493739454],"iteration":289,"passed_time":0.07624629933,"remaining_time":0.1866719742},
{"learn":[4.493162376],"iteration":290,"passed_time":0.07644350897,"remaining_time":0.1862489617},
{"learn":[4.49010921],"iteration":291,"passed_time":0.07664584365,"remaining_time":0.1858399223},
{"learn":[4.485119285],"iteration":292,"passed_time":0.07684634499,"remaining_time":0.18542787},
{"learn":[4.48469937],"iteration":293,"passed_time":0.07711297176,"remaining_time":0.1851760478},
{"learn":[4.481308096],"iteration":294,"passed_time":0.07734743166,"remaining_time":0.1848472519},
{"learn":[4.47732849],"iteration":295,"passed_time":0.07762830853,"remaining_time":0.1846294906},
{"learn":[4.475381771],"iteration":296,"passed_time":0.07787751852,"remaining_time":0.1843363486},
{"learn":[4.470953504],"iteration":297,"passed_time":0.07812714518,"remaining_time":0.1840444829},
{"learn":[4.465588269],"iteration":298,"passed_time":0.07838664691,"remaining_time":0.1837760518},
{"learn":[4.462576433],"iteration":299,"passed_time":0.0786605654,"remaining_time":0.1835413193},
{"learn":[4.461269171],"iteration":300,"passed_time":0.07889406695,"remaining_time":0.1832124678},
{"learn":[4.458567145],"iteration":301,"passed_time":0.07908840158,"remaining_time":0.1827937229},
{"learn":[4.458343057],"iteration":302,"passed_time":0.07929619463,"remaining_time":0.182407418},
{"learn":[4.45766862],"iteration":303,"passed_time":0.07947794584,"remaining_time":0.1819626655},
{"learn":[4.452830425],"iteration":304,"passed_time":0.07969015559,"remaining_time":0.1815890431},
{"learn":[4.447508861],"iteration":305,"passed_time":0.07987582349,"remaining_time":0.1811562794},
{"learn":[4.442016851],"iteration":306,"passed_time":0.08011995012,"remaining_time":0.1808570861},
{"learn":[4.436230014],"iteration":307,"passed_time":0.08029995132,"remaining_time":0.1804141763},
{"learn":[4.434546921],"iteration":308,"passed_time":0.0805176611,"remaining_time":0.1800572939},
{"learn":[4.430438856],"iteration":309,"passed_time":0.08070757903,"remaining_time":0.1796394501},
{"learn":[4.426247968],"iteration":310,"passed_time":0.08093283053,"remaining_time":0.1793013512},
{"learn":[4.426026453],"iteration":311,"passed_time":0.08111762343,"remaining_time":0.1788747594},
{"learn":[4.423404275],"iteration":312,"passed_time":0.08132174979,"remaining_time":0.1784921473},
{"learn":[4.420912265],"iteration":313,"passed_time":0.08154654295,"remaining_time":0.1781558231},
{"learn":[4.413927943],"iteration":314,"passed_time":0.08177558614,"remaining_time":0.1778294492},
{"learn":[4.409524725],"iteration":315,"passed_time":0.08197737915,"remaining_time":0.1774447068},
{"learn":[4.403914406],"iteration":316,"passed_time":0.08218067217,"remaining_time":0.1770643504},
{"learn":[4.401691974],"iteration":317,"passed_time":0.08243363219,"remaining_time":0.1767916263},
{"learn":[4.396325866],"iteration":318,"passed_time":0.08264325858,"remaining_time":0.1764265175},
{"learn":[4.392470574],"iteration":319,"passed_time":0.08284850995,"remaining_time":0.1760530836},
{"learn":[4.388718712],"iteration":320,"passed_time":0.08303701121,"remaining_time":0.1756452667},
{"learn":[4.387074863],"iteration":321,"passed_time":0.08330959635,"remaining_time":0.1754158582},
{"learn":[4.386863656],"iteration":322,"passed_time":0.08358426485,"remaining_time":0.1751905489},
{"learn":[4.38303855],"iteration":323,"passed_time":0.08389076689,"remaining_time":0.1750313531},
{"learn":[4.380335535],"iteration":324,"passed_time":0.08420922734,"remaining_time":0.1748960876},
{"learn":[4.377954458],"iteration":325,"passed_time":0.08442997881,"remaining_time":0.1745576863},
{"learn":[4.374716235],"iteration":326,"passed_time":0.08466581372,"remaining_time":0.1742510478},
{"learn":[4.37280085],"iteration":327,"passed_time":0.08496010734,"remaining_time":0.1740646102},
{"learn":[4.372197164],"iteration":328,"passed_time":0.08516302536,"remaining_time":0.1736911551},
{"learn":[4.366002826],"iteration":329,"passed_time":0.08537298509,"remaining_time":0.1733330303},
{"learn":[4.35945987],"iteration":330,"passed_time":0.08570127894,"remaining_time":0.1732149716},
{"learn":[4.359271807],"iteration":331,"passed_time":0.08594440556,"remaining_time":0.1729242859},
{"learn":[4.35838405],"iteration":332,"passed_time":0.08616203201,"remaining_time":0.1725828089},
{"learn":[4.355119307],"iteration":333,"passed_time":0.086361075,"remaining_time":0.1722050178},
{"learn":[4.353206975],"iteration":334,"passed_time":0.08659524323,"remaining_time":0.1718980201},
{"learn":[4.348722675],"iteration":335,"passed_time":0.08704445455,"remaining_time":0.1720164221},
{"learn":[4.344468362],"iteration":336,"passed_time":0.08746437402,"remaining_time":0.1720738278},
{"learn":[4.342926666],"iteration":337,"passed_time":0.08786041832,"remaining_time":0.1720816477},
{"learn":[4.338942871],"iteration":338,"passed_time":0.0881221284,"remaining_time":0.171825153},
{"learn":[4.334960257],"iteration":339,"passed_time":0.0883326298,"remaining_time":0.1714692225},
{"learn":[4.331054434],"iteration":340,"passed_time":0.08854200619,"remaining_time":0.1711119709},
{"learn":[4.329114521],"iteration":341,"passed_time":0.08875788263,"remaining_time":0.17076809},
{"learn":[4.325009309],"iteration":342,"passed_time":0.08905563461,"remaining_time":0.1705817841},
{"learn":[4.322531179],"iteration":343,"passed_time":0.08924055251,"remaining_time":0.1701796583},
{"learn":[4.319015626],"iteration":344,"passed_time":0.08950813762,"remaining_time":0.1699357395},
{"learn":[4.317695306],"iteration":345,"passed_time":0.08977101438,"remaining_time":0.1696827844},
{"learn":[4.31554801],"iteration":346,"passed_time":0.09008689148,"remaining_time":0.1695295105},
{"learn":[4.310487843],"iteration":347,"passed_time":0.09033651814,"remaining_time":0.1692511777},
{"learn":[4.308289538],"iteration":348,"passed_time":0.09055493626,"remaining_time":0.1689147951},
{"learn":[4.304425836],"iteration":349,"passed_time":0.09075377092,"remaining_time":0.1685427174},
{"learn":[4.30168791],"iteration":350,"passed_time":0.090966689,"remaining_time":0.1681976671},
{"learn":[4.299992616],"iteration":351,"passed_time":0.09118385712,"remaining_time":0.1678611915},
{"learn":[4.297544527],"iteration":352,"passed_time":0.0913613583,"remaining_time":0.1674526879},
{"learn":[4.293431948],"iteration":353,"passed_time":0.09158681813,"remaining_time":0.1671330071},
{"learn":[4.292176392],"iteration":354,"passed_time":0.09183740313,"remaining_time":0.1668595071},
{"learn":[4.28818187],"iteration":355,"passed_time":0.09218903047,"remaining_time":0.1667689203},
{"learn":[4.283186319],"iteration":356,"passed_time":0.09238557345,"remaining_time":0.1663975455},
{"learn":[4.279216536],"iteration":357,"passed_time":0.09262665839,"remaining_time":0.1661070243},
{"learn":[4.276879416],"iteration":358,"passed_time":0.09282278469,"remaining_time":0.1657365041},
{"learn":[4.270832262],"iteration":359,"passed_time":0.09305699459,"remaining_time":0.165434657},
{"learn":[4.26506165],"iteration":360,"passed_time":0.09329812119,"remaining_time":0.1651454278},
{"learn":[4.261178065],"iteration":361,"passed_time":0.0935248727,"remaining_time":0.1648311292},
{"learn":[4.260635086],"iteration":362,"passed_time":0.09381087461,"remaining_time":0.1646212868},
{"learn":[4.258726194],"iteration":363,"passed_time":0.09402908439,"remaining_time":0.164292576},
{"learn":[4.254948583],"iteration":364,"passed_time":0.09423625244,"remaining_time":0.1639452611},
{"learn":[4.249847572],"iteration":365,"passed_time":0.09444500383,"remaining_time":0.1636014547},
{"learn":[4.249274253],"iteration":366,"passed_time":0.09468200541,"remaining_time":0.1633071101},
{"learn":[4.245552012],"iteration":367,"passed_time":0.09493275708,"remaining_time":0.1630366915},
{"learn":[4.243862558],"iteration":368,"passed_time":0.09512605003,"remaining_time":0.1626681235},
{"learn":[4.240668197],"iteration":369,"passed_time":0.09534242647,"remaining_time":0.1623398072},
{"learn":[4.238323876],"iteration":370,"passed_time":0.09567030365,"remaining_time":0.1622011348},
{"learn":[4.238125534],"iteration":371,"passed_time":0.09588918011,"remaining_time":0.1618774331},
{"learn":[4.234701951],"iteration":372,"passed_time":0.09608326474,"remaining_time":0.1615126193},
{"learn":[4.232592291],"iteration":373,"passed_time":0.09630014118,"remaining_time":0.1611868673},
{"learn":[4.229143064],"iteration":374,"passed_time":0.09651018425,"remaining_time":0.1608503071},
{"learn":[4.22741775],"iteration":375,"passed_time":0.09669360213,"remaining_time":0.1604702333},
{"learn":[4.223878357],"iteration":376,"passed_time":0.09689039511,"remaining_time":0.1601133054},
{"learn":[4.22222462],"iteration":377,"passed_time":0.09708035471,"remaining_time":0.1597459805},
{"learn":[4.218448719],"iteration":378,"passed_time":0.09728864776,"remaining_time":0.1594096313},
{"learn":[4.216670896],"iteration":379,"passed_time":0.09753564941,"remaining_time":0.1591371122},
{"learn":[4.211144812],"iteration":380,"passed_time":0.09790440186,"remaining_time":0.1590625322},
{"learn":[4.209976476],"iteration":381,"passed_time":0.09818394539,"remaining_time":0.1588420897},
{"learn":[4.204813746],"iteration":382,"passed_time":0.09840636354,"remaining_time":0.1585293115},
{"learn":[4.201916866],"iteration":383,"passed_time":0.09862653167,"remaining_time":0.1582133946},
{"learn":[4.198194875],"iteration":384,"passed_time":0.09883815808,"remaining_time":0.1578843304},
{"learn":[4.1933911],"iteration":385,"passed_time":0.09910315984,"remaining_time":0.1576407776},
{"learn":[4.191072545],"iteration":386,"passed_time":0.09932407798,"remaining_time":0.1573272863},
{"learn":[4.187619438],"iteration":387,"passed_time":0.09952912101,"remaining_time":0.1569892321},
{"learn":[4.184372135],"iteration":388,"passed_time":0.09977133096,"remaining_time":0.1567102396},
{"learn":[4.182180254],"iteration":389,"passed_time":0.1000431244,"remaining_time":0.1564777074},
{"learn":[4.178508864],"iteration":390,"passed_time":0.1003002095,"remaining_time":0.1562220654},
{"learn":[4.176062949],"iteration":391,"passed_time":0.1006201283,"remaining_time":0.1560638724},
{"learn":[4.175899273],"iteration":392,"passed_time":0.1015037175,"remaining_time":0.1567754619},
{"learn":[4.175509224],"iteration":393,"passed_time":0.1016942604,"remaining_time":0.1564129995},
{"learn":[4.173000496],"iteration":394,"passed_time":0.1020316377,"remaining_time":0.1562763058},
{"learn":[4.170408321],"iteration":395,"passed_time":0.1023044312,"remaining_time":0.156040092},
{"learn":[4.169842222],"iteration":396,"passed_time":0.1026104332,"remaining_time":0.155854134},
{"learn":[4.166828616],"iteration":397,"passed_time":0.1029034351,"remaining_time":0.1556479094},
{"learn":[4.164554361],"iteration":398,"passed_time":0.1031592285,"remaining_time":0.1553852039},
{"learn":[4.159127289],"iteration":399,"passed_time":0.1033865217,"remaining_time":0.1550797825},
{"learn":[4.156229885],"iteration":400,"passed_time":0.1035988981,"remaining_time":0.1547524687},
{"learn":[4.153603388],"iteration":401,"passed_time":0.1038033578,"remaining_time":0.1544139502},
{"learn":[4.14977311],"iteration":402,"passed_time":0.103989734,"remaining_time":0.1540493083},
{"learn":[4.148466417],"iteration":403,"passed_time":0.1042135272,"remaining_time":0.1537407481},
{"learn":[4.146159351],"iteration":404,"passed_time":0.1044553621,"remaining_time":0.1534591123},
{"learn":[4.142827914],"iteration":405,"passed_time":0.1046701136,"remaining_time":0.1531380479},
{"learn":[4.139442873],"iteration":406,"passed_time":0.1048881984,"remaining_time":0.1528223627},
{"learn":[4.13653192],"iteration":407,"passed_time":0.1052071588,"remaining_time":0.1526535246},
{"learn":[4.132439277],"iteration":408,"passed_time":0.1054409104,"remaining_time":0.1523608265},
{"learn":[4.128244703],"iteration":409,"passed_time":0.1056736203,"remaining_time":0.152066917},
{"learn":[4.127677319],"iteration":410,"passed_time":0.1058927884,"remaining_time":0.1517538987},
{"learn":[4.126539112],"iteration":411,"passed_time":0.1061116232,"remaining_time":0.1514408603},
{"learn":[4.121891469],"iteration":412,"passed_time":0.1063170412,"remaining_time":0.1511092087},
{"learn":[4.118348764],"iteration":413,"passed_time":0.1065309593,"remaining_time":0.1507901984},
{"learn":[4.116264635],"iteration":414,"passed_time":0.1067323356,"remaining_time":0.1504540153},
{"learn":[4.114304256],"iteration":415,"passed_time":0.1069437954,"remaining_time":0.1501326358},
{"learn":[4.114164987],"iteration":416,"passed_time":0.1071444634,"remaining_time":0.1497966958},
{"learn":[4.110851632],"iteration":417,"passed_time":0.1073553398,"remaining_time":0.1494756166},
{"learn":[4.105843922],"iteration":418,"passed_time":0.1075513411,"remaining_time":0.1491344372},
{"learn":[4.102623279],"iteration":419,"passed_time":0.1077862177,"remaining_time":0.1488476339},
{"learn":[4.098440752],"iteration":420,"passed_time":0.1080160942,"remaining_time":0.1485542008},
{"learn":[4.093319196],"iteration":421,"passed_time":0.1082612625,"remaining_time":0.1482820135},
{"learn":[4.089940502],"iteration":422,"passed_time":0.1086281399,"remaining_time":0.1481759734},
{"learn":[4.08893464],"iteration":423,"passed_time":0.1088242246,"remaining_time":0.1478366824},
{"learn":[4.088817345],"iteration":424,"passed_time":0.1090568094,"remaining_time":0.1475474481},
{"learn":[4.086757746],"iteration":425,"passed_time":0.1093321863,"remaining_time":0.1473161383},
{"learn":[4.086060933],"iteration":426,"passed_time":0.1095818546,"remaining_time":0.1470501234},
{"learn":[4.081762715],"iteration":427,"passed_time":0.1098153562,"remaining_time":0.1467625788},
{"learn":[4.080485558],"iteration":428,"passed_time":0.1100191075,"remaining_time":0.1464356886},
{"learn":[4.079141109],"iteration":429,"passed_time":0.1102601508,"remaining_time":0.1461588045},
{"learn":[4.076186556],"iteration":430,"passed_time":0.1104603188,"remaining_time":0.1458281239},
{"learn":[4.070499399],"iteration":431,"passed_time":0.1106779452,"remaining_time":0.1455210021},
{"learn":[4.066310675],"iteration":432,"passed_time":0.1109639888,"remaining_time":0.1453038837},
{"learn":[4.063136418],"iteration":433,"passed_time":0.1112382406,"remaining_time":0.1450710696},
{"learn":[4.05978997],"iteration":434,"passed_time":0.111639535,"remaining_time":0.1450030742},
{"learn":[4.057957376],"iteration":435,"passed_time":0.1121444967,"remaining_time":0.1450676517},
{"learn":[4.055871867],"iteration":436,"passed_time":0.1124555404,"remaining_time":0.1448797923},
{"learn":[4.05359987],"iteration":437,"passed_time":0.1126789169,"remaining_time":0.1445788842},
{"learn":[4.051397008],"iteration":438,"passed_time":0.1129244185,"remaining_time":0.1443066032},
{"learn":[4.05110631],"iteration":439,"passed_time":0.1131321699,"remaining_time":0.1439863981},
{"learn":[4.050905397],"iteration":440,"passed_time":0.1133733382,"remaining_time":0.1437090613},
{"learn":[4.050623101],"iteration":441,"passed_time":0.1136675901,"remaining_time":0.1434989034},
{"learn":[4.049284173],"iteration":442,"passed_time":0.1139167168,"remaining_time":0.1432316281},
{"learn":[4.047208373],"iteration":443,"passed_time":0.114252344,"remaining_time":0.1430727552},
{"learn":[4.044241161],"iteration":444,"passed_time":0.1145785545,"remaining_time":0.1429013433},
{"learn":[4.043602397],"iteration":445,"passed_time":0.1149194318,"remaining_time":0.1427474557},
{"learn":[4.043415484],"iteration":446,"passed_time":0.1151213082,"remaining_time":0.1424207683},
{"learn":[4.042048655],"iteration":447,"passed_time":0.1153443096,"remaining_time":0.1421206672},
{"learn":[4.041484944],"iteration":448,"passed_time":0.115551686,"remaining_time":0.141801735},
{"learn":[4.038212943],"iteration":449,"passed_time":0.1158245212,"remaining_time":0.1415633037},
{"learn":[4.037143018],"iteration":450,"passed_time":0.1161657318,"remaining_time":0.1414079529},
{"learn":[4.033552128],"iteration":451,"passed_time":0.1163718998,"remaining_time":0.1410880555},
{"learn":[4.02848618],"iteration":452,"passed_time":0.1167441523,"remaining_time":0.1409692082},
{"learn":[4.026597556],"iteration":453,"passed_time":0.1169416536,"remaining_time":0.1406390812},
{"learn":[4.02648534],"iteration":454,"passed_time":0.1172790725,"remaining_time":0.1404771308},
{"learn":[4.024045386],"iteration":455,"passed_time":0.1175616161,"remaining_time":0.1402489455},
{"learn":[4.021427856],"iteration":456,"passed_time":0.1178036594,"remaining_time":0.1399724005},
{"learn":[4.01639721],"iteration":457,"passed_time":0.1181486617,"remaining_time":0.1398178485},
{"learn":[4.012342452],"iteration":458,"passed_time":0.1183559964,"remaining_time":0.1395002049},
{"learn":[4.008447],"iteration":459,"passed_time":0.1185633727,"remaining_time":0.1391830897},
{"learn":[4.005591809],"iteration":460,"passed_time":0.1187577907,"remaining_time":0.1388512998},
{"learn":[4.002615799],"iteration":461,"passed_time":0.1190195424,"remaining_time":0.1385985148},
{"learn":[4.001089462],"iteration":462,"passed_time":0.1193203778,"remaining_time":0.1383910213},
{"learn":[4.000924775],"iteration":463,"passed_time":0.1196538383,"remaining_time":0.1382208133},
{"learn":[3.999758075],"iteration":464,"passed_time":0.1198731315,"remaining_time":0.1379185491},
{"learn":[3.996329564],"iteration":465,"passed_time":0.1201136331,"remaining_time":0.1376409443},
{"learn":[3.993716264],"iteration":466,"passed_time":0.1203131344,"remaining_time":0.1373167037},
{"learn":[3.990967538],"iteration":467,"passed_time":0.120549886,"remaining_time":0.1370353405},
{"learn":[3.986077218],"iteration":468,"passed_time":0.121000514,"remaining_time":0.1369963175},
{"learn":[3.981942263],"iteration":469,"passed_time":0.1212805992,"remaining_time":0.1367632289},
{"learn":[3.979511137],"iteration":470,"passed_time":0.1214874339,"remaining_time":0.1364476699},
{"learn":[3.978710748],"iteration":471,"passed_time":0.1216770185,"remaining_time":0.1361132749},
{"learn":[3.976632276],"iteration":472,"passed_time":0.1218748115,"remaining_time":0.1357886377},
{"learn":[3.973629365],"iteration":473,"passed_time":0.1220843962,"remaining_time":0.1354776211},
{"learn":[3.971681233],"iteration":474,"passed_time":0.1223612314,"remaining_time":0.135241361},
{"learn":[3.969473374],"iteration":475,"passed_time":0.1225802328,"remaining_time":0.1349412647},
{"learn":[3.967449195],"iteration":476,"passed_time":0.1231454866,"remaining_time":0.135021152},
{"learn":[3.964201367],"iteration":477,"passed_time":0.1234965723,"remaining_time":0.1348644576},
{"learn":[3.961392091],"iteration":478,"passed_time":0.1237141154,"remaining_time":0.1345616996},
{"learn":[3.960555052],"iteration":479,"passed_time":0.1239244918,"remaining_time":0.1342515328},
{"learn":[3.957563554],"iteration":480,"passed_time":0.1243474113,"remaining_time":0.1341711153},
{"learn":[3.954189385],"iteration":481,"passed_time":0.1245967046,"remaining_time":0.1339026825},
{"learn":[3.951677502],"iteration":482,"passed_time":0.1248007059,"remaining_time":0.1335858488},
{"learn":[3.951174462],"iteration":483,"passed_time":0.1249946656,"remaining_time":0.1332587757},
{"learn":[3.950004392],"iteration":484,"passed_time":0.1253055843,"remaining_time":0.1330564452},
{"learn":[3.948566779],"iteration":485,"passed_time":0.1256462949,"remaining_time":0.1328851761},
{"learn":[3.945892579],"iteration":486,"passed_time":0.1259751304,"remaining_time":0.1327007021},
{"learn":[3.944444941],"iteration":487,"passed_time":0.126254299,"remaining_time":0.1324635268},
{"learn":[3.942231768],"iteration":488,"passed_time":0.1264729671,"remaining_time":0.1321629574},
{"learn":[3.941703541],"iteration":489,"passed_time":0.1266627183,"remaining_time":0.1318326252},
{"learn":[3.939293916],"iteration":490,"passed_time":0.1268715947,"remaining_time":0.1315226919},
{"learn":[3.937315443],"iteration":491,"passed_time":0.1270796378,"remaining_time":0.1312123089},
{"learn":[3.935519958],"iteration":492,"passed_time":0.1272782224,"remaining_time":0.1308926141},
{"learn":[3.932131616],"iteration":493,"passed_time":0.1274913905,"remaining_time":0.1305883474},
{"learn":[3.929082532],"iteration":494,"passed_time":0.1278033926,"remaining_time":0.1303852793},
{"learn":[3.927830529],"iteration":495,"passed_time":0.1280895195,"remaining_time":0.1301554795},
{"learn":[3.926085941],"iteration":496,"passed_time":0.1283422712,"remaining_time":0.1298916749},
{"learn":[3.92046034],"iteration":497,"passed_time":0.1285948979,"remaining_time":0.1296277886},
{"learn":[3.917780271],"iteration":498,"passed_time":0.1289326085,"remaining_time":0.1294493724},
{"learn":[3.912146908],"iteration":499,"passed_time":0.1291483599,"remaining_time":0.1291483599},
{"learn":[3.909512239],"iteration":500,"passed_time":0.1293586946,"remaining_time":0.1288422926},
{"learn":[3.907282112],"iteration":501,"passed_time":0.1296246964,"remaining_time":0.1285918303},
{"learn":[3.90568216],"iteration":502,"passed_time":0.1298440312,"remaining_time":0.1282951958},
{"learn":[3.903849431],"iteration":503,"passed_time":0.1300406575,"remaining_time":0.1279765201},
{"learn":[3.90198085],"iteration":504,"passed_time":0.1302462839,"remaining_time":0.1276671495},
{"learn":[3.898886694],"iteration":505,"passed_time":0.1304590769,"remaining_time":0.1273651858},
{"learn":[3.895450146],"iteration":506,"passed_time":0.13066762,"remaining_time":0.1270594411},
{"learn":[3.89382729],"iteration":507,"passed_time":0.1308744547,"remaining_time":0.1267524246},
{"learn":[3.890286637],"iteration":508,"passed_time":0.131070706,"remaining_time":0.1264355926},
{"learn":[3.887655219],"iteration":509,"passed_time":0.1312718324,"remaining_time":0.1261239174},
{"learn":[3.88413899],"iteration":510,"passed_time":0.1315218757,"remaining_time":0.1258594857},
{"learn":[3.881250123],"iteration":511,"passed_time":0.1317287937,"remaining_time":0.1255540065},
{"learn":[3.88098973],"iteration":512,"passed_time":0.1319635453,"remaining_time":0.1252753344},
{"learn":[3.880561174],"iteration":513,"passed_time":0.1321580466,"remaining_time":0.1249587756},
{"learn":[3.87825162],"iteration":514,"passed_time":0.1323997149,"remaining_time":0.1246871101},
{"learn":[3.87523511],"iteration":515,"passed_time":0.1328779681,"remaining_time":0.1246374739},
{"learn":[3.87174933],"iteration":516,"passed_time":0.1333369294,"remaining_time":0.1245681565},
{"learn":[3.870297511],"iteration":517,"passed_time":0.1337591406,"remaining_time":0.1244631385},
{"learn":[3.86955017],"iteration":518,"passed_time":0.1339495585,"remaining_time":0.1241420764},
{"learn":[3.867557245],"iteration":519,"passed_time":0.1341577682,"remaining_time":0.1238379399},
{"learn":[3.865653713],"iteration":520,"passed_time":0.1344430618,"remaining_time":0.1236050415},
{"learn":[3.862549767],"iteration":521,"passed_time":0.134776064,"remaining_time":0.1234156295},
{"learn":[3.859840696],"iteration":522,"passed_time":0.1349910655,"remaining_time":0.1231180463},
{"learn":[3.857657597],"iteration":523,"passed_time":0.1352046085,"remaining_time":0.1228194536},
{"learn":[3.856305353],"iteration":524,"passed_time":0.1355438608,"remaining_time":0.1226349217},
{"learn":[3.854271938],"iteration":525,"passed_time":0.1358481128,"remaining_time":0.1224182614},
{"learn":[3.8501781],"iteration":526,"passed_time":0.136421575,"remaining_time":0.1224428937},
{"learn":[3.848251277],"iteration":527,"passed_time":0.1366833684,"remaining_time":0.1221866475},
{"learn":[3.846812941],"iteration":528,"passed_time":0.1369623286,"remaining_time":0.121945665},
{"learn":[3.843622474],"iteration":529,"passed_time":0.1372507055,"remaining_time":0.1217128898},
{"learn":[3.841530085],"iteration":530,"passed_time":0.1375303324,"remaining_time":0.1214721768},
{"learn":[3.841376363],"iteration":531,"passed_time":0.1377090836,"remaining_time":0.1211425773},
{"learn":[3.840404321],"iteration":532,"passed_time":0.1380102939,"remaining_time":0.1209208391},
{"learn":[3.839230428],"iteration":533,"passed_time":0.1382407538,"remaining_time":0.1206370623},
{"learn":[3.837414321],"iteration":534,"passed_time":0.13843263,"remaining_time":0.1203199495},
{"learn":[3.836673975],"iteration":535,"passed_time":0.1386356314,"remaining_time":0.1200129346},
{"learn":[3.834724455],"iteration":536,"passed_time":0.1388498828,"remaining_time":0.119716007},
{"learn":[3.832192922],"iteration":537,"passed_time":0.1390529258,"remaining_time":0.1194097616},
{"learn":[3.830725157],"iteration":538,"passed_time":0.139232177,"remaining_time":0.1190835503},
{"learn":[3.828775926],"iteration":539,"passed_time":0.1394521368,"remaining_time":0.118792561},
{"learn":[3.826345379],"iteration":540,"passed_time":0.1397748473,"remaining_time":0.1185890109},
{"learn":[3.822059159],"iteration":541,"passed_time":0.139981182,"remaining_time":0.1182866815},
{"learn":[3.82066851],"iteration":542,"passed_time":0.1401773083,"remaining_time":0.117976114},
{"learn":[3.818403247],"iteration":543,"passed_time":0.1403885181,"remaining_time":0.1176786107},
{"learn":[3.815693905],"iteration":544,"passed_time":0.1407232286,"remaining_time":0.1174845303},
{"learn":[3.814141097],"iteration":545,"passed_time":0.1409885221,"remaining_time":0.1172322143},
{"learn":[3.812239199],"iteration":546,"passed_time":0.1412393571,"remaining_time":0.1169678771},
{"learn":[3.809206493],"iteration":547,"passed_time":0.1414439834,"remaining_time":0.1166654754},
{"learn":[3.806842247],"iteration":548,"passed_time":0.1418191526,"remaining_time":0.1165035297},
{"learn":[3.802816757],"iteration":549,"passed_time":0.1421051128,"remaining_time":0.1162678196},
{"learn":[3.802126015],"iteration":550,"passed_time":0.1423514061,"remaining_time":0.1159996032},
{"learn":[3.799855865],"iteration":551,"passed_time":0.1425966161,"remaining_time":0.115730587},
{"learn":[3.797016381],"iteration":552,"passed_time":0.1428044508,"remaining_time":0.1154314458},
{"learn":[3.793973634],"iteration":553,"passed_time":0.143026869,"remaining_time":0.1151443747},
{"learn":[3.791456515],"iteration":554,"passed_time":0.1432235786,"remaining_time":0.1148369234},
{"learn":[3.791049608],"iteration":555,"passed_time":0.1434309133,"remaining_time":0.1145383552},
{"learn":[3.786284958],"iteration":556,"passed_time":0.1436441231,"remaining_time":0.1142447873},
{"learn":[3.78323688],"iteration":557,"passed_time":0.1438528328,"remaining_time":0.1139479428},
{"learn":[3.780572595],"iteration":558,"passed_time":0.144079876,"remaining_time":0.1136658771},
{"learn":[3.780450488],"iteration":559,"passed_time":0.1443445444,"remaining_time":0.1134135706},
{"learn":[3.778179709],"iteration":560,"passed_time":0.1446794216,"remaining_time":0.1132161606},
{"learn":[3.777871194],"iteration":561,"passed_time":0.1450352573,"remaining_time":0.1130345956},
{"learn":[3.775514007],"iteration":562,"passed_time":0.1452645922,"remaining_time":0.1127542216},
{"learn":[3.774711016],"iteration":563,"passed_time":0.1454993021,"remaining_time":0.1124781839},
{"learn":[3.773389646],"iteration":564,"passed_time":0.145743762,"remaining_time":0.1122097991},
{"learn":[3.769954575],"iteration":565,"passed_time":0.1459930554,"remaining_time":0.111945205},
{"learn":[3.769871603],"iteration":566,"passed_time":0.1462483904,"remaining_time":0.1116852787},
{"learn":[3.769753753],"iteration":567,"passed_time":0.1464758086,"remaining_time":0.1114041361},
{"learn":[3.769610982],"iteration":568,"passed_time":0.1467233519,"remaining_time":0.1111384265},
{"learn":[3.768628525],"iteration":569,"passed_time":0.1470187289,"remaining_time":0.1109088656},
{"learn":[3.766908744],"iteration":570,"passed_time":0.1472381887,"remaining_time":0.1106220367},
{"learn":[3.765090588],"iteration":571,"passed_time":0.1475071071,"remaining_time":0.1103724508},
{"learn":[3.762174425],"iteration":572,"passed_time":0.1477490671,"remaining_time":0.1101027079},
{"learn":[3.76051743],"iteration":573,"passed_time":0.1479519434,"remaining_time":0.1098040556},
{"learn":[3.758379267],"iteration":574,"passed_time":0.1481648198,"remaining_time":0.1095131277},
{"learn":[3.752545758],"iteration":575,"passed_time":0.1484067798,"remaining_time":0.1092438796},
{"learn":[3.752328138],"iteration":576,"passed_time":0.1486709065,"remaining_time":0.1089909765},
{"learn":[3.752194809],"iteration":577,"passed_time":0.1488718245,"remaining_time":0.1086918857},
{"learn":[3.751410374],"iteration":578,"passed_time":0.149097951,"remaining_time":0.1084114635},
{"learn":[3.746918093],"iteration":579,"passed_time":0.1493193692,"remaining_time":0.1081278191},
{"learn":[3.743662215],"iteration":580,"passed_time":0.1495219122,"remaining_time":0.1078307766},
{"learn":[3.739125992],"iteration":581,"passed_time":0.1497606221,"remaining_time":0.1075600344},
{"learn":[3.738200596],"iteration":582,"passed_time":0.1500173738,"remaining_time":0.1073023068},
{"learn":[3.736592866],"iteration":583,"passed_time":0.1502332503,"remaining_time":0.1070154659},
{"learn":[3.736130337],"iteration":584,"passed_time":0.1504997104,"remaining_time":0.1067647518},
{"learn":[3.732502199],"iteration":585,"passed_time":0.1507592538,"remaining_time":0.1065090974},
{"learn":[3.729595181],"iteration":586,"passed_time":0.1509870886,"remaining_time":0.1062311203},
{"learn":[3.729465606],"iteration":587,"passed_time":0.1512318403,"remaining_time":0.105965167},
{"learn":[3.729067874],"iteration":588,"passed_time":0.1514352166,"remaining_time":0.1056704143},
{"learn":[3.725773555],"iteration":589,"passed_time":0.1516393013,"remaining_time":0.1053764636},
{"learn":[3.720967504],"iteration":590,"passed_time":0.1518464277,"remaining_time":0.105084922},
{"learn":[3.720740679],"iteration":591,"passed_time":0.1520850959,"remaining_time":0.104815404},
{"learn":[3.719694214],"iteration":592,"passed_time":0.1523088474,"remaining_time":0.1045357519},
{"learn":[3.717988596],"iteration":593,"passed_time":0.152540349,"remaining_time":0.1042615853},
{"learn":[3.716442817],"iteration":594,"passed_time":0.1527471003,"remaining_time":0.1039707154},
{"learn":[3.713236102],"iteration":595,"passed_time":0.1529783936,"remaining_time":0.1036967634},
{"learn":[3.712057637],"iteration":596,"passed_time":0.15319277,"remaining_time":0.1034115348},
{"learn":[3.709656025],"iteration":597,"passed_time":0.1534352716,"remaining_time":0.1031454501},
{"learn":[3.708717846],"iteration":598,"passed_time":0.1536577731,"remaining_time":0.1028660551},
{"learn":[3.708043378],"iteration":599,"passed_time":0.1539154415,"remaining_time":0.1026102943},
{"learn":[3.70774319],"iteration":600,"passed_time":0.1542040684,"remaining_time":0.1023750803},
{"learn":[3.707560098],"iteration":601,"passed_time":0.1544311116,"remaining_time":0.1020989741},
{"learn":[3.705078832],"iteration":602,"passed_time":0.1550951576,"remaining_time":0.1021107423},
{"learn":[3.704747108],"iteration":603,"passed_time":0.1553691595,"remaining_time":0.1018645483},
{"learn":[3.702982937],"iteration":604,"passed_time":0.1556224528,"remaining_time":0.1016047419},
{"learn":[3.70016287],"iteration":605,"passed_time":0.1558749545,"remaining_time":0.1013444424},
{"learn":[3.69908199],"iteration":606,"passed_time":0.1561025394,"remaining_time":0.1010680362},
{"learn":[3.698314845],"iteration":607,"passed_time":0.1563270408,"remaining_time":0.1007898027},
{"learn":[3.698024854],"iteration":608,"passed_time":0.1565297922,"remaining_time":0.1004977812},
{"learn":[3.69619073],"iteration":609,"passed_time":0.1567680021,"remaining_time":0.1002287227},
{"learn":[3.694966654],"iteration":610,"passed_time":0.1569920869,"remaining_time":0.09995077221},
{"learn":[3.690885874],"iteration":611,"passed_time":0.1572608804,"remaining_time":0.09970134248},
{"learn":[3.688466682],"iteration":612,"passed_time":0.1575072987,"remaining_time":0.09943772365},
{"learn":[3.684566378],"iteration":613,"passed_time":0.1577715505,"remaining_time":0.09918537212},
{"learn":[3.679384228],"iteration":614,"passed_time":0.157997927,"remaining_time":0.09890927136},
{"learn":[3.676903447],"iteration":615,"passed_time":0.158197095,"remaining_time":0.09861637089},
{"learn":[3.675128908],"iteration":616,"passed_time":0.158445805,"remaining_time":0.09835452722},
{"learn":[3.672791636],"iteration":617,"passed_time":0.1586867232,"remaining_time":0.09808790983},
{"learn":[3.671455743],"iteration":618,"passed_time":0.158904433,"remaining_time":0.09780709043},
{"learn":[3.670358578],"iteration":619,"passed_time":0.1591282262,"remaining_time":0.09753020313},
{"learn":[3.668095556],"iteration":620,"passed_time":0.1593579777,"remaining_time":0.09725712326},
{"learn":[3.665840022],"iteration":621,"passed_time":0.1596076877,"remaining_time":0.09699631181},
{"learn":[3.663062611],"iteration":622,"passed_time":0.1598471476,"remaining_time":0.09672933331},
{"learn":[3.65996547],"iteration":623,"passed_time":0.1601141911,"remaining_time":0.09647906385},
{"learn":[3.657928305],"iteration":624,"passed_time":0.1603714428,"remaining_time":0.09622286567},
{"learn":[3.654162104],"iteration":625,"passed_time":0.1606677781,"remaining_time":0.09599001438},
{"learn":[3.649931755],"iteration":626,"passed_time":0.1608701544,"remaining_time":0.09570106476},
{"learn":[3.647863421],"iteration":627,"passed_time":0.1610676141,"remaining_time":0.0954094784},
{"learn":[3.645198926],"iteration":628,"passed_time":0.1612565737,"remaining_time":0.09511317779},
{"learn":[3.641581941],"iteration":629,"passed_time":0.1615315338,"remaining_time":0.09486772622},
{"learn":[3.638332117],"iteration":630,"passed_time":0.1618140357,"remaining_time":0.09462659141},
{"learn":[3.636888537],"iteration":631,"passed_time":0.1620755791,"remaining_time":0.09437312202},
{"learn":[3.635762044],"iteration":632,"passed_time":0.1623014556,"remaining_time":0.09409894821},
{"learn":[3.635132313],"iteration":633,"passed_time":0.1625224988,"remaining_time":0.09382213651},
{"learn":[3.633702331],"iteration":634,"passed_time":0.1627809172,"remaining_time":0.09356698387},
{"learn":[3.631077135],"iteration":635,"passed_time":0.1630242938,"remaining_time":0.09330321216},
{"learn":[3.629975622],"iteration":636,"passed_time":0.1632611287,"remaining_time":0.09303577663},
{"learn":[3.628624901],"iteration":637,"passed_time":0.1634761718,"remaining_time":0.09275607239},
{"learn":[3.6273139],"iteration":638,"passed_time":0.1637058816,"remaining_time":0.09248485645},
{"learn":[3.625955875],"iteration":639,"passed_time":0.1639174247,"remaining_time":0.0922035514},
{"learn":[3.623767835],"iteration":640,"passed_time":0.1641880932,"remaining_time":0.09195557793},
{"learn":[3.621390625],"iteration":641,"passed_time":0.1644147197,"remaining_time":0.09168297454},
{"learn":[3.620545937],"iteration":642,"passed_time":0.1646464296,"remaining_time":0.09141333648},
{"learn":[3.619214276],"iteration":643,"passed_time":0.164913723,"remaining_time":0.09116348664},
{"learn":[3.616559667],"iteration":644,"passed_time":0.1651250994,"remaining_time":0.09088280666},
{"learn":[3.61537688],"iteration":645,"passed_time":0.1653445592,"remaining_time":0.09060677084},
{"learn":[3.614166691],"iteration":646,"passed_time":0.1655933525,"remaining_time":0.09034691414},
{"learn":[3.613822023],"iteration":647,"passed_time":0.1658198124,"remaining_time":0.09007495981},
{"learn":[3.611119793],"iteration":648,"passed_time":0.1660448556,"remaining_time":0.0898023795},
{"learn":[3.609137387],"iteration":649,"passed_time":0.1663232324,"remaining_time":0.0895586636},
{"learn":[3.607881079],"iteration":650,"passed_time":0.1665801508,"remaining_time":0.08930333736},
{"learn":[3.606837452],"iteration":651,"passed_time":0.1668461526,"remaining_time":0.08905285443},
{"learn":[3.605135265],"iteration":652,"passed_time":0.1671733631,"remaining_time":0.0888348499},
{"learn":[3.60292965],"iteration":653,"passed_time":0.167409948,"remaining_time":0.08856856575},
{"learn":[3.598862544],"iteration":654,"passed_time":0.1676498662,"remaining_time":0.08830412802},
{"learn":[3.5963556],"iteration":655,"passed_time":0.1679434099,"remaining_time":0.08806788566},
{"learn":[3.593614193],"iteration":656,"passed_time":0.1681744114,"remaining_time":0.08779881752},
{"learn":[3.590614557],"iteration":657,"passed_time":0.1684236214,"remaining_time":0.08753932905},
{"learn":[3.58925267],"iteration":658,"passed_time":0.1686740397,"remaining_time":0.08728049703},
{"learn":[3.588087584],"iteration":659,"passed_time":0.1689405832,"remaining_time":0.08702999739},
{"learn":[3.586888414],"iteration":660,"passed_time":0.1692052099,"remaining_time":0.08677846621},
{"learn":[3.58677556],"iteration":661,"passed_time":0.1694289197,"remaining_time":0.08650600434},
{"learn":[3.585453797],"iteration":662,"passed_time":0.1696808798,"remaining_time":0.08624804899},
{"learn":[3.584658275],"iteration":663,"passed_time":0.1699210064,"remaining_time":0.0859841237},
{"learn":[3.581980979],"iteration":664,"passed_time":0.1701368828,"remaining_time":0.08570805374},
{"learn":[3.578065779],"iteration":665,"passed_time":0.170365301,"remaining_time":0.08543845425},
{"learn":[3.575175005],"iteration":666,"passed_time":0.170616761,"remaining_time":0.08518048187},
{"learn":[3.573193688],"iteration":667,"passed_time":0.1708410542,"remaining_time":0.08490902691},
{"learn":[3.570762412],"iteration":668,"passed_time":0.1710949725,"remaining_time":0.08465237055},
{"learn":[3.568193999],"iteration":669,"passed_time":0.171363391,"remaining_time":0.08440286421},
{"learn":[3.564880673],"iteration":670,"passed_time":0.1716137676,"remaining_time":0.08414445537},
{"learn":[3.563800118],"iteration":671,"passed_time":0.1719618116,"remaining_time":0.08393374138},
{"learn":[3.562147736],"iteration":672,"passed_time":0.1722429802,"remaining_time":0.08369012557},
{"learn":[3.560012626],"iteration":673,"passed_time":0.1725371904,"remaining_time":0.08345270636},
{"learn":[3.559192592],"iteration":674,"passed_time":0.172777692,"remaining_time":0.08318925913},
{"learn":[3.557141538],"iteration":675,"passed_time":0.1730499855,"remaining_time":0.08294111732},
{"learn":[3.555719724],"iteration":676,"passed_time":0.1733068206,"remaining_time":0.08268552887},
{"learn":[3.554901345],"iteration":677,"passed_time":0.173515572,"remaining_time":0.08240710055},
{"learn":[3.553705258],"iteration":678,"passed_time":0.1737354068,"remaining_time":0.08213411718},
{"learn":[3.552189066],"iteration":679,"passed_time":0.1740610339,"remaining_time":0.08191107479},
{"learn":[3.550296163],"iteration":680,"passed_time":0.1743802027,"remaining_time":0.08168470582},
{"learn":[3.550101595],"iteration":681,"passed_time":0.1745956208,"remaining_time":0.0814096883},
{"learn":[3.54774607],"iteration":682,"passed_time":0.1748082889,"remaining_time":0.08113356893},
{"learn":[3.545909001],"iteration":683,"passed_time":0.1750358321,"remaining_time":0.08086450722},
{"learn":[3.545176788],"iteration":684,"passed_time":0.1752888338,"remaining_time":0.08060727392},
{"learn":[3.543924034],"iteration":685,"passed_time":0.1754910018,"remaining_time":0.08032678507},
{"learn":[3.542044489],"iteration":686,"passed_time":0.1757667119,"remaining_time":0.08008003033},
{"learn":[3.54086704],"iteration":687,"passed_time":0.1759779634,"remaining_time":0.07980396013},
{"learn":[3.53939783],"iteration":688,"passed_time":0.1762544652,"remaining_time":0.07955753073},
{"learn":[3.539268029],"iteration":689,"passed_time":0.1764608832,"remaining_time":0.07927952725},
{"learn":[3.537263425],"iteration":690,"passed_time":0.1766736763,"remaining_time":0.07900458174},
{"learn":[3.53609107],"iteration":691,"passed_time":0.1768806777,"remaining_time":0.07872723805},
{"learn":[3.532618368],"iteration":692,"passed_time":0.1771687629,"remaining_time":0.07848601764},
{"learn":[3.531285174],"iteration":693,"passed_time":0.1774050145,"remaining_time":0.07822180756},
{"learn":[3.530906972],"iteration":694,"passed_time":0.1776082242,"remaining_time":0.07794317753},
{"learn":[3.529253194],"iteration":695,"passed_time":0.1778592259,"remaining_time":0.07768563889},
{"learn":[3.526704485],"iteration":696,"passed_time":0.1780948524,"remaining_time":0.07742143514},
{"learn":[3.525011299],"iteration":697,"passed_time":0.1783101039,"remaining_time":0.07714849767},
{"learn":[3.522807037],"iteration":698,"passed_time":0.1790949424,"remaining_time":0.0771209981},
{"learn":[3.520771728],"iteration":699,"passed_time":0.1794081112,"remaining_time":0.07688919051},
{"learn":[3.518189893],"iteration":700,"passed_time":0.1796798213,"remaining_time":0.0766394673},
{"learn":[3.514780145],"iteration":701,"passed_time":0.1799095312,"remaining_time":0.07637185227},
{"learn":[3.514485081],"iteration":702,"passed_time":0.1801745746,"remaining_time":0.07611927264},
{"learn":[3.511453244],"iteration":703,"passed_time":0.1803703676,"remaining_time":0.07583754092},
{"learn":[3.509246742],"iteration":704,"passed_time":0.180580869,"remaining_time":0.0755622076},
{"learn":[3.508872591],"iteration":705,"passed_time":0.180836954,"remaining_time":0.07530604035},
{"learn":[3.506008247],"iteration":706,"passed_time":0.1810707889,"remaining_time":0.07504065227},
{"learn":[3.50225327],"iteration":707,"passed_time":0.1812847904,"remaining_time":0.07476717342},
{"learn":[3.500352616],"iteration":708,"passed_time":0.1815600839,"remaining_time":0.0745190189},
{"learn":[3.497795726],"iteration":709,"passed_time":0.181782877,"remaining_time":0.07424934413},
{"learn":[3.497700485],"iteration":710,"passed_time":0.1819746283,"remaining_time":0.07396718365},
{"learn":[3.496734765],"iteration":711,"passed_time":0.1822141715,"remaining_time":0.07370460871},
{"learn":[3.493144427],"iteration":712,"passed_time":0.182429423,"remaining_time":0.07343232033},
{"learn":[3.491259098],"iteration":713,"passed_time":0.1826670912,"remaining_time":0.07316917099},
{"learn":[3.485001703],"iteration":714,"passed_time":0.1828995511,"remaining_time":0.07290401687},
{"learn":[3.484187037],"iteration":715,"passed_time":0.1831550945,"remaining_time":0.0726481101},
{"learn":[3.483704185],"iteration":716,"passed_time":0.1833760126,"remaining_time":0.07237853775},
{"learn":[3.481457592],"iteration":717,"passed_time":0.1836468477,"remaining_time":0.07212870622},
{"learn":[3.48118214],"iteration":718,"passed_time":0.1839190996,"remaining_time":0.07187936993},
{"learn":[3.480737036],"iteration":719,"passed_time":0.1841812263,"remaining_time":0.07162603245},
{"learn":[3.480006515],"iteration":720,"passed_time":0.1843852277,"remaining_time":0.07135017825},
{"learn":[3.477936458],"iteration":721,"passed_time":0.1846316876,"remaining_time":0.07109087142},
{"learn":[3.47679351],"iteration":722,"passed_time":0.1849681482,"remaining_time":0.07086608168},
{"learn":[3.471463763],"iteration":723,"passed_time":0.1852074415,"remaining_time":0.07060394178},
{"learn":[3.471043257],"iteration":724,"passed_time":0.1853972344,"remaining_time":0.07032308891},
{"learn":[3.469554304],"iteration":725,"passed_time":0.1855984857,"remaining_time":0.07004681142},
{"learn":[3.468410453],"iteration":726,"passed_time":0.1858256539,"remaining_time":0.06978047252},
{"learn":[3.467168815],"iteration":727,"passed_time":0.1861009891,"remaining_time":0.06953223768},
{"learn":[3.465600892],"iteration":728,"passed_time":0.1863254906,"remaining_time":0.06926503148},
{"learn":[3.463176275],"iteration":729,"passed_time":0.1866084925,"remaining_time":0.06901957941},
{"learn":[3.462797982],"iteration":730,"passed_time":0.1868458274,"remaining_time":0.06875721965},
{"learn":[3.460791158],"iteration":731,"passed_time":0.1870751622,"remaining_time":0.06849199929},
{"learn":[3.455874275],"iteration":732,"passed_time":0.1873708725,"remaining_time":0.06825105453},
{"learn":[3.455763362],"iteration":733,"passed_time":0.1875925407,"remaining_time":0.06798312782},
{"learn":[3.453569421],"iteration":734,"passed_time":0.1878014171,"remaining_time":0.067710715},
{"learn":[3.453160426],"iteration":735,"passed_time":0.1880322936,"remaining_time":0.06744636619},
{"learn":[3.448845152],"iteration":736,"passed_time":0.18824467,"remaining_time":0.0671755064},
{"learn":[3.448304504],"iteration":737,"passed_time":0.1885173385,"remaining_time":0.06692620961},
{"learn":[3.448174582],"iteration":738,"passed_time":0.1887727569,"remaining_time":0.06667075716},
{"learn":[3.446651845],"iteration":739,"passed_time":0.1889905083,"remaining_time":0.06640207049},
{"learn":[3.444960819],"iteration":740,"passed_time":0.1892310099,"remaining_time":0.06614147311},
{"learn":[3.444012556],"iteration":741,"passed_time":0.189437303,"remaining_time":0.06586903526},
{"learn":[3.443144758],"iteration":742,"passed_time":0.1896821379,"remaining_time":0.06561010693},
{"learn":[3.439986863],"iteration":743,"passed_time":0.1899018894,"remaining_time":0.0653425856},
{"learn":[3.436819281],"iteration":744,"passed_time":0.1901325159,"remaining_time":0.06507891485},
{"learn":[3.434569773],"iteration":745,"passed_time":0.1904743515,"remaining_time":0.06485319744},
{"learn":[3.433484162],"iteration":746,"passed_time":0.1907186032,"remaining_time":0.06459411861},
{"learn":[3.431464493],"iteration":747,"passed_time":0.1910153551,"remaining_time":0.06435276671},
{"learn":[3.430516186],"iteration":748,"passed_time":0.1912793569,"remaining_time":0.06410029183},
{"learn":[3.430373411],"iteration":749,"passed_time":0.1915194418,"remaining_time":0.06383981394},
{"learn":[3.427920801],"iteration":750,"passed_time":0.1917893186,"remaining_time":0.06358926809},
{"learn":[3.427818995],"iteration":751,"passed_time":0.1920127784,"remaining_time":0.06332336311},
{"learn":[3.424959353],"iteration":752,"passed_time":0.192241155,"remaining_time":0.06305918364},
{"learn":[3.424650459],"iteration":753,"passed_time":0.192496365,"remaining_time":0.06280385383},
{"learn":[3.42304513],"iteration":754,"passed_time":0.192697283,"remaining_time":0.06253090641},
{"learn":[3.420137366],"iteration":755,"passed_time":0.1929041177,"remaining_time":0.06226005916},
{"learn":[3.417084612],"iteration":756,"passed_time":0.1931529527,"remaining_time":0.06200286329},
{"learn":[3.41583214],"iteration":757,"passed_time":0.194099209,"remaining_time":0.06196834905},
{"learn":[3.414407214],"iteration":758,"passed_time":0.1943620024,"remaining_time":0.06171441711},
{"learn":[3.412430295],"iteration":759,"passed_time":0.1945825039,"remaining_time":0.06144710649},
{"learn":[3.410375397],"iteration":760,"passed_time":0.1948274222,"remaining_time":0.06118758726},
{"learn":[3.407556776],"iteration":761,"passed_time":0.1950408403,"remaining_time":0.0609182677},
{"learn":[3.406060958],"iteration":762,"passed_time":0.1952775085,"remaining_time":0.06065631654},
{"learn":[3.401529116],"iteration":763,"passed_time":0.1955424686,"remaining_time":0.06040317093},
{"learn":[3.398389895],"iteration":764,"passed_time":0.1957466783,"remaining_time":0.06013133255},
{"learn":[3.396625717],"iteration":765,"passed_time":0.1960027633,"remaining_time":0.05987551779},
{"learn":[3.394643203],"iteration":766,"passed_time":0.1962773902,"remaining_time":0.05962533496},
{"learn":[3.393587179],"iteration":767,"passed_time":0.1964903499,"remaining_time":0.05935645987},
{"learn":[3.392948541],"iteration":768,"passed_time":0.1967091847,"remaining_time":0.05908949502},
{"learn":[3.389948022],"iteration":769,"passed_time":0.1969277278,"remaining_time":0.05882256806},
{"learn":[3.388930922],"iteration":770,"passed_time":0.1971717711,"remaining_time":0.05856334058},
{"learn":[3.388156925],"iteration":771,"passed_time":0.1973648141,"remaining_time":0.05828909017},
{"learn":[3.387255134],"iteration":772,"passed_time":0.1976235241,"remaining_time":0.05803433374},
{"learn":[3.386371259],"iteration":773,"passed_time":0.1978839009,"remaining_time":0.05778005374},
{"learn":[3.384534425],"iteration":774,"passed_time":0.1980842772,"remaining_time":0.05750833854},
{"learn":[3.383373969],"iteration":775,"passed_time":0.1983191121,"remaining_time":0.05724675401},
{"learn":[3.38306962],"iteration":776,"passed_time":0.1985549053,"remaining_time":0.05698551337},
{"learn":[3.382392408],"iteration":777,"passed_time":0.1987605317,"remaining_time":0.05671573013},
{"learn":[3.380602869],"iteration":778,"passed_time":0.1989861999,"remaining_time":0.0564517974},
{"learn":[3.379013233],"iteration":779,"passed_time":0.1991771595,"remaining_time":0.05617817319},
{"learn":[3.375932717],"iteration":780,"passed_time":0.199408036,"remaining_time":0.05591595376},
{"learn":[3.374114255],"iteration":781,"passed_time":0.1996415376,"remaining_time":0.05565454628},
{"learn":[3.37066323],"iteration":782,"passed_time":0.1998809558,"remaining_time":0.05539484983},
{"learn":[3.369765279],"iteration":783,"passed_time":0.2001157074,"remaining_time":0.05513391939},
{"learn":[3.368247121],"iteration":784,"passed_time":0.2004180844,"remaining_time":0.05489157726},
{"learn":[3.367664757],"iteration":785,"passed_time":0.2006739194,"remaining_time":0.05463641064},
{"learn":[3.364284944],"iteration":786,"passed_time":0.200955088,"remaining_time":0.05438809878},
{"learn":[3.364058843],"iteration":787,"passed_time":0.2012011313,"remaining_time":0.0541302536},
{"learn":[3.362380684],"iteration":788,"passed_time":0.2014604247,"remaining_time":0.05387598176},
{"learn":[3.36176512],"iteration":789,"passed_time":0.2016758428,"remaining_time":0.05361003416},
{"learn":[3.360737141],"iteration":790,"passed_time":0.2019092193,"remaining_time":0.05334895935},
{"learn":[3.360623725],"iteration":791,"passed_time":0.2021779295,"remaining_time":0.053097234},
{"learn":[3.358967078],"iteration":792,"passed_time":0.20250839,"remaining_time":0.05286158478},
{"learn":[3.357808268],"iteration":793,"passed_time":0.2027804751,"remaining_time":0.05261055149},
{"learn":[3.356676044],"iteration":794,"passed_time":0.2030470186,"remaining_time":0.05235803624},
{"learn":[3.35657406],"iteration":795,"passed_time":0.2033157287,"remaining_time":0.05210604103},
{"learn":[3.355485939],"iteration":796,"passed_time":0.2035822721,"remaining_time":0.051853452},
{"learn":[3.354393867],"iteration":797,"passed_time":0.203807732,"remaining_time":0.0515904284},
{"learn":[3.351777623],"iteration":798,"passed_time":0.2040601087,"remaining_time":0.05133427014},
{"learn":[3.350223949],"iteration":799,"passed_time":0.2043031519,"remaining_time":0.05107578799},
{"learn":[3.349557604],"iteration":800,"passed_time":0.2045008616,"remaining_time":0.05080608172},
{"learn":[3.346895548],"iteration":801,"passed_time":0.204713613,"remaining_time":0.05054026855},
{"learn":[3.344937855],"iteration":802,"passed_time":0.204915031,"remaining_time":0.05027180711},
{"learn":[3.343608835],"iteration":803,"passed_time":0.2051022406,"remaining_time":0.0500000487},
{"learn":[3.343425009],"iteration":804,"passed_time":0.2053088253,"remaining_time":0.04973319371},
{"learn":[3.341550413],"iteration":805,"passed_time":0.2054962016,"remaining_time":0.04946186489},
{"learn":[3.337073596],"iteration":806,"passed_time":0.2057120363,"remaining_time":0.0491975502},
{"learn":[3.336730726],"iteration":807,"passed_time":0.2058965792,"remaining_time":0.04892591982},
{"learn":[3.334027983],"iteration":808,"passed_time":0.2060718721,"remaining_time":0.04865232084},
{"learn":[3.33263303],"iteration":809,"passed_time":0.2062372898,"remaining_time":0.04837664823},
{"learn":[3.331017924],"iteration":810,"passed_time":0.2064360828,"remaining_time":0.04810902546},
{"learn":[3.329701589],"iteration":811,"passed_time":0.206611584,"remaining_time":0.04783617954},
{"learn":[3.329119598],"iteration":812,"passed_time":0.2068370438,"remaining_time":0.0475750642},
{"learn":[3.326706689],"iteration":813,"passed_time":0.2070348368,"remaining_time":0.04730771455},
{"learn":[3.325509934],"iteration":814,"passed_time":0.2072186714,"remaining_time":0.04703736712},
{"learn":[3.324999464],"iteration":815,"passed_time":0.2073821724,"remaining_time":0.04676264673},
{"learn":[3.322869212],"iteration":816,"passed_time":0.207562007,"remaining_time":0.04649185713},
{"learn":[3.321344675],"iteration":817,"passed_time":0.2077445499,"remaining_time":0.04622189251},
{"learn":[3.321256728],"iteration":818,"passed_time":0.2079303428,"remaining_time":0.04595285963},
{"learn":[3.321176476],"iteration":819,"passed_time":0.2081354275,"remaining_time":0.04568826456},
{"learn":[3.320494591],"iteration":820,"passed_time":0.2083438038,"remaining_time":0.04542453214},
{"learn":[3.317762987],"iteration":821,"passed_time":0.2085407218,"remaining_time":0.04515845315},
{"learn":[3.316919484],"iteration":822,"passed_time":0.2087311814,"remaining_time":0.04489115324},
{"learn":[3.315319931],"iteration":823,"passed_time":0.2089065159,"remaining_time":0.04462080923},
{"learn":[3.313987519],"iteration":824,"passed_time":0.2090980589,"remaining_time":0.0443541337},
{"learn":[3.313855276],"iteration":825,"passed_time":0.20926206,"remaining_time":0.0440818383},
{"learn":[3.312116881],"iteration":826,"passed_time":0.2094485195,"remaining_time":0.04381450288},
{"learn":[3.31010731],"iteration":827,"passed_time":0.209622604,"remaining_time":0.04354479214},
{"learn":[3.309183831],"iteration":828,"passed_time":0.2098019386,"remaining_time":0.04327639505},
{"learn":[3.307653395],"iteration":829,"passed_time":0.2100353151,"remaining_time":0.04301928141},
{"learn":[3.306664985],"iteration":830,"passed_time":0.2102782334,"remaining_time":0.0427641654},
{"learn":[3.305340487],"iteration":831,"passed_time":0.2105601103,"remaining_time":0.04251694534},
{"learn":[3.302038508],"iteration":832,"passed_time":0.2107724867,"remaining_time":0.04225570862},
{"learn":[3.29977897],"iteration":833,"passed_time":0.2109715713,"remaining_time":0.04199194346},
{"learn":[3.298833688],"iteration":834,"passed_time":0.2112760734,"remaining_time":0.0417491642},
{"learn":[3.298090218],"iteration":835,"passed_time":0.2115112833,"remaining_time":0.04149264409},
{"learn":[3.297291613],"iteration":836,"passed_time":0.2117517849,"remaining_time":0.04123720542},
{"learn":[3.296686105],"iteration":837,"passed_time":0.2120007449,"remaining_time":0.04098343755},
{"learn":[3.294801255],"iteration":838,"passed_time":0.2122577466,"remaining_time":0.04073122431},
{"learn":[3.292333869],"iteration":839,"passed_time":0.2124717063,"remaining_time":0.04047080121},
{"learn":[3.291197252],"iteration":840,"passed_time":0.212725208,"remaining_time":0.04021796442},
{"learn":[3.288899471],"iteration":841,"passed_time":0.2129693763,"remaining_time":0.03996337465},
{"learn":[3.287682089],"iteration":842,"passed_time":0.2132100863,"remaining_time":0.03970816553},
{"learn":[3.287323931],"iteration":843,"passed_time":0.2134629629,"remaining_time":0.03945523959},
{"learn":[3.28653243],"iteration":844,"passed_time":0.2136645059,"remaining_time":0.03919289754},
{"learn":[3.284137134],"iteration":845,"passed_time":0.2138762157,"remaining_time":0.0389325499},
{"learn":[3.282667936],"iteration":846,"passed_time":0.2141579259,"remaining_time":0.03868496182},
{"learn":[3.279527567],"iteration":847,"passed_time":0.2143928858,"remaining_time":0.03842891349},
{"learn":[3.277603802],"iteration":848,"passed_time":0.2146365541,"remaining_time":0.03817446368},
{"learn":[3.277495769],"iteration":849,"passed_time":0.2148440138,"remaining_time":0.03791364949},
{"learn":[3.276516972],"iteration":850,"passed_time":0.2151216823,"remaining_time":0.03766525342},
{"learn":[3.275325877],"iteration":851,"passed_time":0.2153758507,"remaining_time":0.03741270645},
{"learn":[3.27385673],"iteration":852,"passed_time":0.2156120189,"remaining_time":0.03715705367},
{"learn":[3.273352119],"iteration":853,"passed_time":0.2158535205,"remaining_time":0.03690235831},
{"learn":[3.272543621],"iteration":854,"passed_time":0.216075772,"remaining_time":0.03664442917},
{"learn":[3.27117865],"iteration":855,"passed_time":0.2163026068,"remaining_time":0.03638735442},
{"learn":[3.270296039],"iteration":856,"passed_time":0.2165621502,"remaining_time":0.03613580803},
{"learn":[3.269645043],"iteration":857,"passed_time":0.2167904018,"remaining_time":0.03587906416},
{"learn":[3.267977864],"iteration":858,"passed_time":0.2170827787,"remaining_time":0.03563291245},
{"learn":[3.267424891],"iteration":859,"passed_time":0.2174211976,"remaining_time":0.03539414845},
{"learn":[3.265753323],"iteration":860,"passed_time":0.217671741,"remaining_time":0.03514096631},
{"learn":[3.263956351],"iteration":861,"passed_time":0.2179644512,"remaining_time":0.03489454092},
{"learn":[3.262787655],"iteration":862,"passed_time":0.2182557448,"remaining_time":0.03464778336},
{"learn":[3.261412982],"iteration":863,"passed_time":0.2185007048,"remaining_time":0.03439362946},
{"learn":[3.261097209],"iteration":864,"passed_time":0.2187694149,"remaining_time":0.03414320349},
{"learn":[3.257891308],"iteration":865,"passed_time":0.2190483335,"remaining_time":0.03389431488},
{"learn":[3.255295204],"iteration":866,"passed_time":0.2192719599,"remaining_time":0.03363687505},
{"learn":[3.252853174],"iteration":867,"passed_time":0.2195191283,"remaining_time":0.03338309324},
{"learn":[3.250409533],"iteration":868,"passed_time":0.2197733383,"remaining_time":0.03313038816},
{"learn":[3.249573602],"iteration":869,"passed_time":0.2201539241,"remaining_time":0.03289656338},
{"learn":[3.247298619],"iteration":870,"passed_time":0.2203750506,"remaining_time":0.03263878476},
{"learn":[3.245238326],"iteration":871,"passed_time":0.2206138855,"remaining_time":0.03238368962},
{"learn":[3.242663121],"iteration":872,"passed_time":0.2208664289,"remaining_time":0.03213062597},
{"learn":[3.241876805],"iteration":873,"passed_time":0.2211784726,"remaining_time":0.03188614136},
{"learn":[3.239846159],"iteration":874,"passed_time":0.2214282243,"remaining_time":0.03163260347},
{"learn":[3.23796587],"iteration":875,"passed_time":0.2216160172,"remaining_time":0.03137030381},
{"learn":[3.236252444],"iteration":876,"passed_time":0.2218771023,"remaining_time":0.03111845334},
{"learn":[3.236057004],"iteration":877,"passed_time":0.2221061455,"remaining_time":0.03086212955},
{"learn":[3.235243791],"iteration":878,"passed_time":0.2223298553,"remaining_time":0.03060513367},
{"learn":[3.232781303],"iteration":879,"passed_time":0.2226001071,"remaining_time":0.03035456006},
{"learn":[3.230189231],"iteration":880,"passed_time":0.2229649845,"remaining_time":0.03011672322},
{"learn":[3.225966867],"iteration":881,"passed_time":0.2232100695,"remaining_time":0.02986257166},
{"learn":[3.225025683],"iteration":882,"passed_time":0.2234943631,"remaining_time":0.02961363588},
{"learn":[3.222419791],"iteration":883,"passed_time":0.2237789483,"remaining_time":0.02936465837},
{"learn":[3.219575472],"iteration":884,"passed_time":0.2242477847,"remaining_time":0.02913954265},
{"learn":[3.217023481],"iteration":885,"passed_time":0.224481203,"remaining_time":0.02888358593},
{"learn":[3.215897474],"iteration":886,"passed_time":0.2246954544,"remaining_time":0.02862523827},
{"learn":[3.214074742],"iteration":887,"passed_time":0.2249329976,"remaining_time":0.02836992763},
{"learn":[3.209587177],"iteration":888,"passed_time":0.225180916,"remaining_time":0.02811595239},
{"learn":[3.207998095],"iteration":889,"passed_time":0.2253985424,"remaining_time":0.02785824681},
{"learn":[3.205736329],"iteration":890,"passed_time":0.2256553774,"remaining_time":0.02760542777},
{"learn":[3.205227121],"iteration":891,"passed_time":0.2258539621,"remaining_time":0.02734554698},
{"learn":[3.20262455],"iteration":892,"passed_time":0.2260893803,"remaining_time":0.0270902169},
{"learn":[3.200428692],"iteration":893,"passed_time":0.2263087151,"remaining_time":0.02683302439},
{"learn":[3.200339316],"iteration":894,"passed_time":0.2264997164,"remaining_time":0.02657259243},
{"learn":[3.198702364],"iteration":895,"passed_time":0.2267942184,"remaining_time":0.02632432892},
{"learn":[3.198444266],"iteration":896,"passed_time":0.2270048864,"remaining_time":0.0260663359},
{"learn":[3.197810611],"iteration":897,"passed_time":0.2272116795,"remaining_time":0.02580800814},
{"learn":[3.195459269],"iteration":898,"passed_time":0.2274658062,"remaining_time":0.02555511282},
{"learn":[3.191685018],"iteration":899,"passed_time":0.2277537248,"remaining_time":0.02530596942},
{"learn":[3.190207938],"iteration":900,"passed_time":0.2279513094,"remaining_time":0.02504681424},
{"learn":[3.189458654],"iteration":901,"passed_time":0.2282283946,"remaining_time":0.02479643311},
{"learn":[3.188862073],"iteration":902,"passed_time":0.2284882296,"remaining_time":0.02454413984},
{"learn":[3.187811291],"iteration":903,"passed_time":0.2287388563,"remaining_time":0.024290852},
{"learn":[3.18644223],"iteration":904,"passed_time":0.2289822329,"remaining_time":0.02403680898},
{"learn":[3.1835864],"iteration":905,"passed_time":0.2292581931,"remaining_time":0.02378617015},
{"learn":[3.181035682],"iteration":906,"passed_time":0.2295046531,"remaining_time":0.02353245065},
{"learn":[3.178430254],"iteration":907,"passed_time":0.2297348629,"remaining_time":0.02327710065},
{"learn":[3.175929401],"iteration":908,"passed_time":0.2299609061,"remaining_time":0.02302138884},
{"learn":[3.17472972],"iteration":909,"passed_time":0.2301877826,"remaining_time":0.02276582466},
{"learn":[3.173824493],"iteration":910,"passed_time":0.2304620761,"remaining_time":0.02251495584},
{"learn":[3.167936361],"iteration":911,"passed_time":0.2306877026,"remaining_time":0.02225933973},
{"learn":[3.167346145],"iteration":912,"passed_time":0.2308933707,"remaining_time":0.02200188746},
{"learn":[3.16266963],"iteration":913,"passed_time":0.2311317056,"remaining_time":0.02174762219},
{"learn":[3.160252231],"iteration":914,"passed_time":0.2313820406,"remaining_time":0.0214945065},
{"learn":[3.15950682],"iteration":915,"passed_time":0.2316105004,"remaining_time":0.02123939087},
{"learn":[3.159143318],"iteration":916,"passed_time":0.2318957107,"remaining_time":0.02098946999},
{"learn":[3.158520946],"iteration":917,"passed_time":0.2321800876,"remaining_time":0.0207393978},
{"learn":[3.158456016],"iteration":918,"passed_time":0.2324077141,"remaining_time":0.02048424901},
{"learn":[3.157843184],"iteration":919,"passed_time":0.2326965077,"remaining_time":0.02023447893},
{"learn":[3.157663422],"iteration":920,"passed_time":0.2329310509,"remaining_time":0.01997997071},
{"learn":[3.156038862],"iteration":921,"passed_time":0.2331663441,"remaining_time":0.01972556924},
{"learn":[3.155023692],"iteration":922,"passed_time":0.2334677628,"remaining_time":0.01947672561},
{"learn":[3.154452558],"iteration":923,"passed_time":0.2337506397,"remaining_time":0.01922624309},
{"learn":[3.152664652],"iteration":924,"passed_time":0.2339828079,"remaining_time":0.01897157902},
{"learn":[3.151889047],"iteration":925,"passed_time":0.234243768,"remaining_time":0.01871926439},
{"learn":[3.149584989],"iteration":926,"passed_time":0.2344886863,"remaining_time":0.01846566785},
{"learn":[3.148027914],"iteration":927,"passed_time":0.2347426046,"remaining_time":0.01821278829},
{"learn":[3.14574609],"iteration":928,"passed_time":0.2349559394,"remaining_time":0.01795680484},
{"learn":[3.1455954],"iteration":929,"passed_time":0.2351669408,"remaining_time":0.01770073748},
{"learn":[3.145526833],"iteration":930,"passed_time":0.2353765255,"remaining_time":0.01744466193},
{"learn":[3.144036588],"iteration":931,"passed_time":0.2355905269,"remaining_time":0.0171890084},
{"learn":[3.143910816],"iteration":932,"passed_time":0.2358180701,"remaining_time":0.01693441661},
{"learn":[3.141395663],"iteration":933,"passed_time":0.2360499883,"remaining_time":0.01668019189},
{"learn":[3.138368325],"iteration":934,"passed_time":0.2362892399,"remaining_time":0.0164265247},
{"learn":[3.137916115],"iteration":935,"passed_time":0.2364889912,"remaining_time":0.01617018744},
{"learn":[3.136307622],"iteration":936,"passed_time":0.2367243678,"remaining_time":0.01591636625},
{"learn":[3.13620222],"iteration":937,"passed_time":0.2369195358,"remaining_time":0.01565992667},
{"learn":[3.134766548],"iteration":938,"passed_time":0.2371612041,"remaining_time":0.01540663839},
{"learn":[3.13265901],"iteration":939,"passed_time":0.2374717895,"remaining_time":0.01515777379},
{"learn":[3.129092952],"iteration":940,"passed_time":0.2376851242,"remaining_time":0.01490268048},
{"learn":[3.12676379],"iteration":941,"passed_time":0.2379383759,"remaining_time":0.01465013355},
{"learn":[3.125801639],"iteration":942,"passed_time":0.2381653774,"remaining_time":0.01439599842},
{"learn":[3.124728864],"iteration":943,"passed_time":0.2384055457,"remaining_time":0.01414270186},
{"learn":[3.123021416],"iteration":944,"passed_time":0.2387013393,"remaining_time":0.01389267054},
{"learn":[3.120976781],"iteration":945,"passed_time":0.2389336742,"remaining_time":0.01363892009},
{"learn":[3.119906424],"iteration":946,"passed_time":0.2391375505,"remaining_time":0.01338362215},
{"learn":[3.119026074],"iteration":947,"passed_time":0.239352052,"remaining_time":0.01312901551},
{"learn":[3.117370458],"iteration":948,"passed_time":0.2395925536,"remaining_time":0.01287589066},
{"learn":[3.116710084],"iteration":949,"passed_time":0.2398527636,"remaining_time":0.01262382967},
{"learn":[3.116306709],"iteration":950,"passed_time":0.2401014736,"remaining_time":0.012371159},
{"learn":[3.114009495],"iteration":951,"passed_time":0.2403076,"remaining_time":0.01211634958},
{"learn":[3.1137069],"iteration":952,"passed_time":0.2405278515,"remaining_time":0.01186233895},
{"learn":[3.111102422],"iteration":953,"passed_time":0.2407889782,"remaining_time":0.01161037002},
{"learn":[3.110313758],"iteration":954,"passed_time":0.2410093963,"remaining_time":0.0113564637},
{"learn":[3.108880581],"iteration":955,"passed_time":0.241254898,"remaining_time":0.01110378192},
{"learn":[3.106473812],"iteration":956,"passed_time":0.2415275248,"remaining_time":0.01085233392},
{"learn":[3.10542031],"iteration":957,"passed_time":0.2417874015,"remaining_time":0.01060028274},
{"learn":[3.104088144],"iteration":958,"passed_time":0.2420182364,"remaining_time":0.01034697361},
{"learn":[3.103416877],"iteration":959,"passed_time":0.2422336545,"remaining_time":0.01009306894},
{"learn":[3.101632859],"iteration":960,"passed_time":0.2424324058,"remaining_time":0.009838567978},
{"learn":[3.100452901],"iteration":961,"passed_time":0.2426671157,"remaining_time":0.009585603323},
{"learn":[3.098528678],"iteration":962,"passed_time":0.2429658677,"remaining_time":0.009335137181},
{"learn":[3.098436012],"iteration":963,"passed_time":0.2432375362,"remaining_time":0.009083559442},
{"learn":[3.09778899],"iteration":964,"passed_time":0.2435022879,"remaining_time":0.0088316892},
{"learn":[3.096584662],"iteration":965,"passed_time":0.243755748,"remaining_time":0.008579394856},
{"learn":[3.095772935],"iteration":966,"passed_time":0.2439616243,"remaining_time":0.008325474253},
{"learn":[3.094345794],"iteration":967,"passed_time":0.2442177094,"remaining_time":0.008073312706},
{"learn":[3.092699946],"iteration":968,"passed_time":0.2445280448,"remaining_time":0.007822878625},
{"learn":[3.092573882],"iteration":969,"passed_time":0.2447342128,"remaining_time":0.007569099365},
{"learn":[3.091857833],"iteration":970,"passed_time":0.2449935895,"remaining_time":0.007317007308},
{"learn":[3.090707225],"iteration":971,"passed_time":0.2451940075,"remaining_time":0.007063201863},
{"learn":[3.087881864],"iteration":972,"passed_time":0.2454893012,"remaining_time":0.006812138881},
{"learn":[3.087800463],"iteration":973,"passed_time":0.2456973442,"remaining_time":0.006558656006},
{"learn":[3.085828197],"iteration":974,"passed_time":0.2459087206,"remaining_time":0.006305351811},
{"learn":[3.085658441],"iteration":975,"passed_time":0.2461492639,"remaining_time":0.006052850752},
{"learn":[3.084343764],"iteration":976,"passed_time":0.2463460152,"remaining_time":0.005799343244},
{"learn":[3.083101027],"iteration":977,"passed_time":0.2466246837,"remaining_time":0.005547794522},
{"learn":[3.080521826],"iteration":978,"passed_time":0.2468773104,"remaining_time":0.005295631786},
{"learn":[3.07970649],"iteration":979,"passed_time":0.2471501456,"remaining_time":0.005043880522},
{"learn":[3.075528655],"iteration":980,"passed_time":0.2474947312,"remaining_time":0.004793475935},
{"learn":[3.07246207],"iteration":981,"passed_time":0.2477539412,"remaining_time":0.004541314605},
{"learn":[3.072332072],"iteration":982,"passed_time":0.2479740677,"remaining_time":0.004288463023},
{"learn":[3.068873235],"iteration":983,"passed_time":0.2482476945,"remaining_time":0.004036547879},
{"learn":[3.068534066],"iteration":984,"passed_time":0.2485065296,"remaining_time":0.003784363395},
{"learn":[3.067546065],"iteration":985,"passed_time":0.2487324478,"remaining_time":0.003531698041},
{"learn":[3.065517038],"iteration":986,"passed_time":0.2489771161,"remaining_time":0.003279333849},
{"learn":[3.063245824],"iteration":987,"passed_time":0.2492257844,"remaining_time":0.003027033818},
{"learn":[3.06226556],"iteration":988,"passed_time":0.2494618693,"remaining_time":0.002774601175},
{"learn":[3.059463091],"iteration":989,"passed_time":0.2497009959,"remaining_time":0.002522232282},
{"learn":[3.057706334],"iteration":990,"passed_time":0.249920039,"remaining_time":0.002269707721},
{"learn":[3.057429154],"iteration":991,"passed_time":0.2501255404,"remaining_time":0.002017141455},
{"learn":[3.056376224],"iteration":992,"passed_time":0.2503537502,"remaining_time":0.001764830062},
{"learn":[3.054357714],"iteration":993,"passed_time":0.2505858768,"remaining_time":0.001512590805},
{"learn":[3.052784918],"iteration":994,"passed_time":0.2508227117,"remaining_time":0.001260415637},
{"learn":[3.052671519],"iteration":995,"passed_time":0.2510490049,"remaining_time":0.001008228935},
{"learn":[3.052628436],"iteration":996,"passed_time":0.2512847981,"remaining_time":0.0007561227626},
{"learn":[3.052242069],"iteration":997,"passed_time":0.2515055496,"remaining_time":0.0005040191374},
{"learn":[3.051154518],"iteration":998,"passed_time":0.2517467178,"remaining_time":0.0002519987165},
{"learn":[3.049861132],"iteration":999,"passed_time":0.2519685526,"remaining_time":0}
]}